Workbook

Sheet Macro
I1: Projetado
A2: Macro | D2: 2020 | E2: 2021 | F2: 2022 | G2: 2023 | H2: 2024 | I2: 2025 | J2: 2026 | K2: 2027 | L2: 2028 | M2: 2029 | N2: 2030
B4: =CHOOSE($C$11,B13,B20,B27) -> [2] Cenário Base
B5: IPCA | D5: 0.0452 | E5: 0.1006 | F5: 0.0579 | G5: 0.0462 | H5: 0.0483 | I5: 0.055 | J5: 0.045 | K5: 0.04 | L5: 0.038 | M5: 0.04 | N5: 0.04
B6: Selic | D6: 0.02 | E6: 0.0442 | F6: 0.1239 | G6: 0.1304 | H6: 0.1088 | I6: 0.1475 | J6: 0.125 | K6: 0.105 | L6: 0.1 | M6: =L6 -> 0.1 | N6: =M6 -> 0.1
B7: PIB | D7: -0.033 | E7: 0.048 | F7: 0.03 | G7: 0.032 | H7: 0.034 | I7: 0.0202 | J7: 0.017 | K7: 0.02 | L7: 0.02 | M7: =L7 -> 0.02 | N7: =M7 -> 0.02
B8: Câmbio | D8: 5.22 | E8: 5.67 | F8: 5.29 | G8: 4.84 | H8: 6.19 | I8: 5.82 | J8: 5.9 | K8: 5.8 | L8: 5.85 | M8: =L8 -> 5.85 | N8: =M8 -> 5.85
B9: Minério de Ferro US$/t | D9: 155.6 | E9: 121.05 | F9: 127.85 | G9: 131.05 | H9: 106.25 | I9: 100 | J9: 95 | K9: 90 | L9: =AVERAGE(I9:K9) -> 95 | M9: =L9 -> 95 | N9: =M9 -> 95
B11: Escolher Cenário | C11: 2 | E11: [1] Cenário Pessimista / [2] Cenário Base / [3] Cenário Otimista
B13: [1] Cenário Pessimista
B14: IPCA | D14: 0.0452 | E14: 0.1006 | F14: 0.0579 | G14: 0.0462 | H14: 0.0483
B15: Selic | D15: 0.02 | E15: 0.0442 | F15: 0.1239 | G15: 0.1304 | H15: 0.1088
B16: PIB | D16: -0.033 | E16: 0.048 | F16: 0.03 | G16: 0.032 | H16: 0.034
B17: Câmbio | D17: 5.22 | E17: 5.67 | F17: 5.29 | G17: 4.84 | H17: 6.19
B18: Minério de Ferro US$/t | D18: 155.6 | E18: 121.05 | F18: 127.85 | G18: 131.05 | H18: 106.25
B20: [2] Cenário Base
B21: IPCA | D21: 0.0452 | E21: 0.1006 | F21: 0.0579 | G21: 0.0462 | H21: 0.0483
B22: Selic | D22: 0.02 | E22: 0.0442 | F22: 0.1239 | G22: 0.1304 | H22: 0.1088
B23: PIB | D23: -0.033 | E23: 0.048 | F23: 0.03 | G23: 0.032 | H23: 0.034
B24: Câmbio | D24: 5.22 | E24: 5.67 | F24: 5.29 | G24: 4.84 | H24: 6.19
B25: Minério de Ferro US$/t | D25: 155.6 | E25: 121.05 | F25: 127.85 | G25: 131.05 | H25: 106.25
B27: [2] Cenário Otimista
B28: IPCA | D28: 0.0452 | E28: 0.1006 | F28: 0.0579 | G28: 0.0462 | H28: 0.0483
B29: Selic | D29: 0.02 | E29: 0.0442 | F29: 0.1239 | G29: 0.1304 | H29: 0.1088
B30: PIB | D30: -0.033 | E30: 0.048 | F30: 0.03 | G30: 0.032 | H30: 0.034
B31: Câmbio | D31: 5.22 | E31: 5.67 | F31: 5.29 | G31: 4.84 | H31: 6.19
B32: Minério de Ferro US$/t | D32: 155.6 | E32: 121.05 | F32: 127.85 | G32: 131.05 | H32: 106.25

Sheet Dados Financeiros
J1: Projetado
B2: Dados Financeiros | E2: 2020 | F2: 2021 | G2: 2022 | H2: 2023 | I2: 2024 | J2: 2025 | K2: 2026 | L2: 2027 | M2: 2028 | N2: 2029 | O2: 2030
B5: Premissas
B7: Crescimento Receita (Var. %) | F7: =F24/E24-1 -> 0.42419626 | G7: =G24/F24-1 -> -0.22831523 | H7: =H24/G24-1 -> -0.081418758 | I7: =I24/H24-1 -> -0.0099055108 | J7: =Macro!I5 -> 0.055 | K7: =Macro!J5 -> 0.045 | L7: =Macro!K5 -> 0.04 | M7: =Macro!L5 -> 0.038 | N7: =Macro!M5 -> 0.04 | O7: =Macro!N5 -> 0.04
B8: CPV (% Receita) | E8: =-E25/E24 -> 0.36076041 | F8: =-F25/F24 -> 0.34371295 | G8: =-G25/G24 -> 0.47599202 | H8: =-H25/H24 -> 0.50328261 | I8: =-I25/I24 -> 0.55723405 | J8: =AVERAGE(G8:I8) -> 0.51216956 | K8: =J8 -> 0.51216956 | L8: =K8 -> 0.51216956 | M8: =L8 -> 0.51216956 | N8: =M8 -> 0.51216956 | O8: =N8 -> 0.51216956
B9: Despesas com Vendas/Administrativas (% Receita Líq.) | E9: =-E27/E24 -> 0.012270861 | F9: =-F27/F24 -> 0.0088612856 | G9: =-G27/G24 -> 0.011734685 | H9: =-H27/H24 -> 0.013255409 | I9: =-I27/I24 -> 0.016489891 | J9: =AVERAGE(E9:I9) -> 0.012522426 | K9: =J9 -> 0.012522426 | L9: =K9 -> 0.012522426 | M9: =L9 -> 0.012522426 | N9: =M9 -> 0.012522426 | O9: =N9 -> 0.012522426
B10: Despesas com P&D (% Receita Líq.) | E10: =-E28/E24 -> 0.010436783 | F10: =-F28/F24 -> 0.010097982 | G10: =-G28/G24 -> 0.015059071 | H10: =-H28/H24 -> 0.01729259 | I10: =-I28/I24 -> 0.02090726 | J10: =I10 -> 0.02090726 | K10: =J10 -> 0.02090726 | L10: =K10 -> 0.02090726 | M10: =L10 -> 0.02090726 | N10: =M10 -> 0.02090726 | O10: =N10 -> 0.02090726
B11: Outras Receitas (Despesas) Operacionais | E11: =E31 -> -4202 | F11: =F31 -> -2212 | G11: =G31 -> -8901 | H11: =H31 -> -7422 | I11: =I31 -> -8275 | J11: =AVERAGE(E11:I11) -> -6202.4 | K11: =J11 -> -6202.4 | L11: =K11 -> -6202.4 | M11: =L11 -> -6202.4 | N11: =M11 -> -6202.4 | O11: =N11 -> -6202.4
B12: Depreciação (% Imobilizado) | E12: =-E33/E63 -> 0.063312289 | F12: =-F33/F63 -> 0.057615326 | G12: =-G33/G63 -> 0.056892665 | H12: =-H33/H63 -> 0.052647697 | I12: =-I33/I63 -> 0.052846347 | J12: =I12 -> 0.052846347 | K12: =J12 -> 0.052846347 | L12: =K12 -> 0.052846347 | M12: =L12 -> 0.052846347 | N12: =M12 -> 0.052846347 | O12: =N12 -> 0.052846347
B13: Aliquota de Depreciação | F13: =-F33/((F63+E63)/2) -> 0.059949453 | G13: =-G33/((G63+F63)/2) -> 0.057251715 | H13: =-H33/((H63+G63)/2) -> 0.052895053 | I13: =-I33/((I63+H63)/2) -> 0.054781124 | J13: =I13 -> 0.054781124 | K13: =J13 -> 0.054781124 | L13: =K13 -> 0.054781124 | M13: =L13 -> 0.054781124 | N13: =M13 -> 0.054781124 | O13: =N13 -> 0.054781124
B14: Juros (% Dívida) | E14: =-(E36+E37)/(E67+E74) -> 0.19332036 | F14: =-(F36+F37)/(F67+F74) -> 0.092576942 | G14: =-(G36+G37)/(G67+G74) -> 0.052329263 | H14: =-(H36+H37)/(H67+H74) -> 0.084753623 | I14: =-(I36+I37)/(I67+I74) -> 0.062086508 | J14: =AVERAGE(G14:I14) -> 0.066389798 | K14: =J14 -> 0.066389798 | L14: =K14 -> 0.066389798 | M14: =L14 -> 0.066389798 | N14: =M14 -> 0.066389798 | O14: =N14 -> 0.066389798
B15: Imposto de Renda (% LAIR) | E15: =-E40/E39 -> 0.12048224 | F15: =-F40/F39 -> 0.15909819 | G15: =-G40/G39 -> 0.14930583 | H15: =-H40/H39 -> 0.27000756 | I15: =-I40/I39 -> 0.11082866 | J15: 0.13 | K15: 0.13 | L15: 0.13 | M15: 0.13 | N15: 0.13 | O15: 0.13
B16: PMR (dias) | E16: =E56*365/E24 -> 45.94688 | F16: =F56*365/F24 -> 27.158256 | G16: =G56*365/G24 -> 36.31662 | H16: =H56*365/H24 -> 35.641119 | I16: =I56*365/I24 -> 25.868304 | J16: =AVERAGE(G16:I16) -> 32.608681 | K16: =J16 -> 32.608681 | L16: =K16 -> 32.608681 | M16: =L16 -> 32.608681 | N16: =M16 -> 32.608681 | O16: =N16 -> 32.608681 | R16: 103.6
B17: PME (dias) | E17: =-E58*365/E25 -> 103.59634 | F17: =-F58*365/F25 -> 88.381026 | G17: =-G58*365/G25 -> 79.170902 | H17: =-H58*365/H25 -> 79.050336 | I17: =-I58*365/I25 -> 90.660972 | J17: =AVERAGE(G17:I17) -> 82.960737 | K17: =J17 -> 82.960737 | L17: =K17 -> 82.960737 | M17: =L17 -> 82.960737 | N17: =M17 -> 82.960737 | O17: =N17 -> 82.960737
B18: PMP (dias) | E18: =-E66*365/E25 -> 85.889283 | F18: =-F66*365/F25 -> 70.161417 | G18: =-G66*365/G25 -> 78.805279 | H18: =-H66*365/H25 -> 88.963434 | I18: =-I66*365/I25 -> 83.360527 | J18: =AVERAGE(G18:I18) -> 83.709747 | K18: =J18 -> 83.709747 | L18: =K18 -> 83.709747 | M18: =L18 -> 83.709747 | N18: =M18 -> 83.709747 | O18: =N18 -> 83.709747
B19: Capex (R$) | E19: 21720 | F19: 27301 | G19: 28184 | H19: 29446 | I19: 35098 | J19: =I19*(1+J13) -> 37020.708 | K19: =J19*(1+K13) -> 39048.744 | L19: =K19*(1+L13) -> 41187.878 | M19: =L19*(1+M13) -> 43444.196 | N19: =M19*(1+N13) -> 45824.118 | O19: =N19*(1+O13) -> 48334.415
B22: DRE
B24: Receita Líquida | E24: 206098 | F24: 293524 | G24: 226508 | H24: 208066 | I24: 206005 | J24: =I24*(1+J7) -> 217335.27 | K24: =J24*(1+K7) -> 227115.36 | L24: =K24*(1+L7) -> 236199.98 | M24: =L24*(1+M7) -> 245175.58 | N24: =M24*(1+N7) -> 254982.6 | O24: =N24*(1+O7) -> 265181.9
B25: CPV | E25: =-90949-E33 -> -74352 | F25: =-117267-F33 -> -100888 | G25: =-124195-G33 -> -107816 | H25: =-120016-H33 -> -104716 | I25: =-131318-I33 -> -114793 | J25: =-J24*J8 -> -111312.51 | K25: =-K24*K8 -> -116321.58 | L25: =-L24*L8 -> -120974.44 | M25: =-M24*M8 -> -125571.47 | N25: =-N24*N8 -> -130594.33 | O25: =-O24*O8 -> -135818.1
B26: Lucro Bruto | E26: =E24+E25 -> 131746 | F26: =F24+F25 -> 192636 | G26: =G24+G25 -> 118692 | H26: =H24+H25 -> 103350 | I26: =I24+I25 -> 91212 | J26: =J24+J25 -> 106022.76 | K26: =K24+K25 -> 110793.79 | L26: =L24+L25 -> 115225.54 | ... O26: =O24+O25 -> 129363.8
B27: Despesa com vendas e administrativas | E27: -2529 | F27: -2601 | G27: -2658 | H27: -2758 | I27: -3397 | J27: =-J24*J9 -> -2721.565 | K27: =-K24*K9 -> -2844.0354 | L27: =-L24*L9 -> -2957.7968 | M27: =-M24*M9 -> -3070.1931 | N27: =-N24*N9 -> -3193.0008 | O27: =-O24*O9 -> -3320.7209
B28: Pesquisa e desenvolvimento | E28: -2151 | F28: -2964 | G28: -3411 | H28: -3598 | I28: -4307 | J28: =-J24*J10 -> -4543.885 | K28: =-K24*K10 -> -4748.3598 | L28: =-L24*L10 -> -4938.2942 | M28: =-M24*M10 -> -5125.9494 | N28: =-N24*N10 -> -5330.9874 | O28: =-O24*O10 -> -5544.2269
B29: Pré-operacionais | E29: -4517 | F29: -3467 | G29: -2466 | H29: -2249 | I29: -2189 | J29: =I29 -> -2189 | K29: =J29 -> -2189 | L29: =K29 -> -2189 | M29: =L29 -> -2189 | N29: =M29 -> -2189 | O29: =N29 -> -2189
B30: Evento Brumadinho | E30: -27016 | F30: -14379
B31: Outras despesas operacionais | E31: -4202 | F31: -2212 | G31: -8901 | H31: -7422 | I31: -8275 | J31: =J11 -> -6202.4 | K31: =K11 -> -6202.4 | L31: =L11 -> -6202.4 | M31: =M11 -> -6202.4 | N31: =N11 -> -6202.4 | O31: =O11 -> -6202.4
B32: Redução/reversão ao valor recuperável | E32: -6968 | F32: -2352 | G32: 3833 | H32: -1317 | I32: 510 | J32: =AVERAGE(E32:I32) -> -1258.8 | K32: =AVERAGE(F32:J32) -> -116.96 | L32: =AVERAGE(G32:K32) -> 330.048 | M32: =AVERAGE(H32:L32) -> -370.5424 | N32: =AVERAGE(I32:M32) -> -181.25088 | O32: =AVERAGE(J32:N32) -> -319.50106
B33: Depreciação | E33: -16597 | F33: -16379 | G33: -16379 | H33: -15300 | I33: -16525 | J33: =-I63*J13+J19*J13/2 -> -16115.985 | K33: =-J63*K13+K19*K13/2 -> -18088.472 | L33: =-K63*L13+L19*L13/2 -> -20169.014 | M33: =-L63*M13+M19*M13/2 -> -22363.53 | N33: =-M63*N13+N19*N13/2 -> -24678.265 | O33: =-N63*O13+O19*O13/2 -> -27119.803
B34: Total de despesas | E34: =SUM(E27:E33) -> -63980 | F34: =SUM(F27:F33) -> -44354 | G34: =SUM(G27:G33) -> -29982 | H34: =SUM(H27:H33) -> -32644 | I34: =SUM(I27:I33) -> -34183 | J34: =SUM(J27:J33) -> -33031.635 | K34: =SUM(K27:K33) -> -34189.227 | L34: =SUM(L27:L33) -> -36126.457 | ... O34: =SUM(O27:O33) -> -44695.652
B35: EBIT | E35: =E26+E34 -> 67766 | F35: =F26+F34 -> 148282 | G35: =G26+G34 -> 88710 | H35: =H26+H34 -> 70706 | I35: =I26+I34 -> 57029 | J35: =J26+J34 -> 72991.128 | K35: =K26+K34 -> 76604.56 | L35: =L26+L34 -> 79099.082 | ... O35: =O26+O34 -> 84668.153
B36: Despesas financeiras | E36: -16666 | F36: -8942 | G36: -6156 | H36: -7276 | I36: -7968 | J36: =AVERAGE(E36:I36) -> -9401.6 | K36: =J36 -> -9401.6 | L36: =K36 -> -9401.6 | M36: =L36 -> -9401.6 | N36: =M36 -> -9401.6 | O36: =N36 -> -9401.6
B37: Receitas financeiras | E37: 1570 | F37: 1822 | G37: 2685 | H37: 2159 | I37: 2281 | J37: =AVERAGE(E37:I37) -> 2103.4 | K37: =J37 -> 2103.4 | L37: =K37 -> 2103.4 | M37: =L37 -> 2103.4 | N37: =M37 -> 2103.4 | O37: =N37 -> 2103.4
B38: Resultado não operacional | E38: -14266 | F38: 17985 | G38: 16465 | H38: -10035 | I38: -17118 | J38: =AVERAGE(E38:I38) -> -1393.8 | K38: =J38 -> -1393.8 | L38: =K38 -> -1393.8 | M38: =L38 -> -1393.8 | N38: =M38 -> -1393.8 | O38: =N38 -> -1393.8
B39: LAIR | E39: =E35+E36+E37+E38 -> 38404 | F39: =F35+F36+F37+F38 -> 159147 | G39: =G35+G36+G37+G38 -> 101704 | H39: =H35+H36+H37+H38 -> 55554 | I39: =I35+I36+I37+I38 -> 34224 | J39: =J35+J36+J37+J38 -> 64299.128 | K39: =K35+K36+K37+K38 -> 67912.56 | L39: =L35+L36+L37+L38 -> 70407.082 | ... O39: =O35+O36+O37+O38 -> 75976.153
B40: IR | E40: -4627 | F40: -25320 | G40: -15185 | H40: -15000 | I40: -3793 | J40: =-J39*J15 -> -8358.8867 | K40: =-K39*K15 -> -8828.6328 | L40: =-L39*L15 -> -9152.9207 | M40: =-M39*M15 -> -9306.7643 | N40: =-N39*N15 -> -9609.7781 | O40: =-O39*O15 -> -9876.8999
B41: Resultado operações descontinuadas | E41: -7065 | F41: -11417 | G41: 9818
B42: Lucro Líquido | E42: =E39+E40+E41 -> 26712 | F42: =F39+F40+F41 -> 122410 | G42: =G39+G40+G41 -> 96337 | H42: =H39+H40+H41 -> 40554 | I42: =I39+I40+I41 -> 30431 | J42: =J39+J40+J41 -> 55940.242 | K42: =K39+K40+K41 -> 59083.928 | L42: =L39+L40+L41 -> 61254.161 | ... O42: =O39+O40+O41 -> 66099.253
B44: EBITDA Ajustado | E44: 87340 | F44: 168056 | G44: 102057 | H44: 92594 | I44: 80121
B45: Margem EBITDA Ajustado | E45: =E44/E24 -> 0.42377898 | F45: =F44/F24 -> 0.57254603 | G45: =G44/G24 -> 0.45056687 | H45: =H44/H24 -> 0.44502225 | I45: =I44/I24 -> 0.38892745
B46: EBIT Ajustado | E46: 70661 | F46: 151677 | G46: 85671 | H46: 77294 | I46: 63596
B47: Margem EBIT Ajustado | E47: =E46/E24 -> 0.34285146 | F47: =F46/F24 -> 0.5167448 | G47: =G46/G24 -> 0.37822505 | H47: =H46/H24 -> 0.37148789 | I47: =I46/I24 -> 0.30871095
B48: NOPAT Ajustado | E48: =E46-E40 -> 75288 | F48: =F46-F40 -> 176997 | G48: =G46-G40 -> 100856 | H48: =H46-H40 -> 92294 | I48: =I46-I40 -> 67389
B49: Margem Líquida | E49: =E42/E24 -> 0.12960824 | F49: =F42/F24 -> 0.41703574 | G49: =G42/G24 -> 0.4253139 | H49: =H42/H24 -> 0.19490931 | I49: =I42/I24 -> 0.14771972
B52: Balanço Patrimonial
B54: Caixa e equivalente caixa | E54: 70086 | F54: 65409 | G54: 24711 | H54: 17474 | I54: 30671 | J54: =I54+J103 -> 22073.748 | K54: =J54+K103 -> 50476.23 | L54: =K54+L103 -> 78599.759 | M54: =L54+M103 -> 110287.7 | N54: =M54+N103 -> 147137.04 | O54: =N54+O103 -> 178280.56
B55: Aplicações financeiras de curto prazo | E55: 4006 | F55: 1028 | G55: 320 | H55: 250 | I55: 331 | J55: =I55*(1+Macro!I6) -> 379.8225 | K55: =J55*(1+Macro!J6) -> 427.30031 | L55: =K55*(1+Macro!K6) -> 472.16685 | M55: =L55*(1+Macro!L6) -> 519.38353 | N55: =M55*(1+Macro!M6) -> 571.32188 | O55: =N55*(1+Macro!N6) -> 628.45407
B56: Contas a receber | E56: 25944 | F56: 21840 | G56: 22537 | H56: 20317 | I56: 14600 | J56: =J24*J16/365 -> 19416.484 | K56: =K24*K16/365 -> 20290.226 | L56: =L24*L16/365 -> 21101.835 | M56: =M24*M16/365 -> 21903.705 | N56: =N24*N16/365 -> 22779.853 | O56: =O24*O16/365 -> 23691.047
B57: Outros | E57: =10978+4693 -> 15671 | F57: =1415+10270 -> 11685 | G57: 10194 | H57: 31461 | I57: 12136 | J57: =I57 -> 12136 | K57: =J57 -> 12136 | L57: =K57 -> 12136 | M57: =L57 -> 12136 | N57: =M57 -> 12136 | O57: =N57 -> 12136
B58: Estoques | E58: 21103 | F58: 24429 | G58: 23386 | H58: 22679 | I58: 28513 | J58: =-J25*J17/365 -> 25300.186 | K58: =-K25*K17/365 -> 26438.695 | L58: =-L25*L17/365 -> 27496.243 | M58: =-M25*M17/365 -> 28541.1 | N58: =-N25*N17/365 -> 29682.744 | O58: =-O25*O17/365 -> 30870.054
B59: Tributos a recuperar | E59: =2646+5670 -> 8316 | F59: =4809+5220 -> 10029 | G59: =6639+5793 -> 12432 | H59: =4355+6652 -> 11007 | I59: =6811+8030 -> 14841 | J59: =AVERAGE(E59:I59) -> 11325 | K59: =AVERAGE(F59:J59) -> 11926.8 | L59: =AVERAGE(G59:K59) -> 12306.36 | M59: =AVERAGE(H59:L59) -> 12281.232 | N59: =AVERAGE(I59:M59) -> 12536.078 | O59: =AVERAGE(J59:N59) -> 12075.094
B60: Depositos judiciais | E60: 6591 | F60: 6808 | G60: 6338 | H60: =2956+3861 -> 6817 | I60: 3326 | J60: =I60 -> 3326 | K60: =J60 -> 3326 | L60: =K60 -> 3326 | M60: =L60 -> 3326 | N60: =M60 -> 3326 | O60: =N60 -> 3326
B61: Tributos diferidos | E61: 53711 | F61: 63847 | G61: 56195 | H61: 46307 | I61: =51050 -> 51050 | J61: =AVERAGE(E61:I61) -> 54222 | K61: =AVERAGE(F61:J61) -> 54324.2 | L61: =AVERAGE(G61:K61) -> 52419.64 | M61: =AVERAGE(H61:L61) -> 51664.568 | N61: =AVERAGE(I61:M61) -> 52736.082 | O61: =AVERAGE(J61:N61) -> 53073.298
B62: Investimentos | E62: 10557 | F62: 9771 | G62: 9381 | H62: 9061 | I62: 28158 | J62: =AVERAGE(E62:I62) -> 13385.6 | K62: =J62 -> 13385.6 | L62: =K62 -> 13385.6 | M62: =L62 -> 13385.6 | N62: =M62 -> 13385.6 | O62: =N62 -> 13385.6
B63: Imobilizado e Intangível | E63: 262145 | F63: 284282 | G63: 287893 | H63: 290611 | I63: 312699 | J63: =I63+J19 -> 349719.71 | K63: =J63+K19 -> 388768.45 | L63: =K63+L19 -> 429956.33 | M63: =L63+M19 -> 473400.53 | N63: =M63+N19 -> 519224.64 | O63: =N63+O19 -> 567559.06
B64: Ativo Total | E64: =SUM(E54:E63) -> 478130 | F64: =SUM(F54:F63) -> 499128 | G64: =SUM(G54:G63) -> 453387 | H64: =SUM(H54:H63) -> 455984 | I64: =SUM(I54:I63) -> 496325
B66: Fornecedores | E66: 17496 | F66: 19393 | G66: 23278 | H66: 25523 | I66: 26217 | J66: =-J25*J18/365 -> 25528.609 | K66: =-K25*K18/365 -> 26677.396 | L66: =-L25*L18/365 -> 27744.492 | M66: =-M25*M18/365 -> 28798.783 | N66: =-N25*N18/365 -> 29950.734 | O66: =-O25*O18/365 -> 31148.763
B67: Empréstimos e financiamentos CP | E67: 5901 | F67: 6720 | G67: 2552 | H67: 3986 | I67: 6316 | J67: =AVERAGE(E67:I67) -> 5095 | K67: =AVERAGE(F67:J67) -> 4933.8 | L67: =AVERAGE(G67:K67) -> 4576.56 | M67: =AVERAGE(H67:L67) -> 4981.472 | N67: =AVERAGE(I67:M67) -> 5180.5664 | O67: =AVERAGE(J67:N67) -> 4953.4797
B68: Arrendamentos | H68: =954+6075 -> 7029 | I68: =907+3507 -> 4414 | J68: =AVERAGE(H68:I68) -> 5721.5 | K68: =J68 -> 5721.5 | L68: =K68 -> 5721.5 | M68: =L68 -> 5721.5 | N68: =M68 -> 5721.5 | O68: =N68 -> 5721.5
B69: Tributos a recolher | E69: =4950 -> 4950 | F69: =12150+10962 -> 23112 | G69: =2454 -> 2454 | H69: =6361 -> 6361 | I69: 3559 | J69: =AVERAGE(G69:I69) -> 4124.6667 | K69: =J69 -> 4124.6667 | L69: =K69 -> 4124.6667 | M69: =L69 -> 4124.6667 | N69: =M69 -> 4124.6667 | O69: =N69 -> 4124.6667
B70: REFIS | E70: =1769+12493 -> 14262 | F70: =1810 -> 1810 | G70: =1934+9753 -> 11687 | H70: =2071+8343 -> 10414 | I70: =2184+6234 -> 8418 | J70: =I70 -> 8418 | K70: =J70 -> 8418 | L70: =K70 -> 8418 | M70: =L70 -> 8418 | N70: =M70 -> 8418 | O70: =N70 -> 8418
B71: Provisões | E71: 65224 | F71: 70133 | G71: 55630 | H71: 42257 | I71: 41961 | J71: =I71 -> 41961 | K71: =J71 -> 41961 | L71: =K71 -> 41961 | M71: =L71 -> 41961 | N71: =M71 -> 41961 | O71: =N71 -> 41961
B72: Passivos relacionados a brumadinho | E72: =9925+13849 -> 23774 | F72: =6449+13288 -> 19737 | G72: =4926+12356 -> 17282 | H72: =5119+9695 -> 14814 | I72: =4420+7778 -> 12198 | J72: =I72 -> 12198 | K72: =J72 -> 12198 | L72: =K72 -> 12198 | M72: =L72 -> 12198 | N72: =M72 -> 12198 | O72: =N72 -> 12198
B73: Dividendos a pagar | E73: 6342 | G73: 7214 | I73: 2046
B74: Empréstimos e financiamentos LP | E74: 72187 | F74: 70189 | G74: 63778 | H74: 56389 | I74: 85282 | J74: =AVERAGE(E74:I74) -> 69565 | K74: =AVERAGE(F74:J74) -> 69040.6 | L74: =AVERAGE(G74:K74) -> 68810.92 | M74: =AVERAGE(H74:L74) -> 69817.504 | N74: =AVERAGE(I74:M74) -> 72503.205 | O74: =AVERAGE(J74:N74) -> 69947.446
B75: Debêntures participativas | E75: 17737 | F75: 19078 | G75: 14218 | H75: 13912 | I75: 13727 | J75: =AVERAGE(G75:I75) -> 13952.333 | K75: =J75 -> 13952.333 | L75: =K75 -> 13952.333 | M75: =L75 -> 13952.333 | N75: =M75 -> 13952.333 | O75: =N75 -> 13952.333
B76: Tributos diferidos | E76: 9198 | F76: 10494 | G76: 7372 | H76: 4210 | I76: 2757 | J76: =I76 -> 2757 | K76: =J76 -> 2757 | L76: =K76 -> 2757 | M76: =L76 -> 2757 | N76: =M76 -> 2757 | O76: =N76 -> 2757
B77: Streaming | E77: 10419 | F77: 9927 | G77: 8411 | H77: 9499 | I77: 11651 | J77: =AVERAGE(E77:I77) -> 9981.4 | K77: =J77 -> 9981.4 | L77: =K77 -> 9981.4 | M77: =L77 -> 9981.4 | N77: =M77 -> 9981.4 | O77: =N77 -> 9981.4
B78: Outros | E78: 49654 | F78: 51477 | G78: 44617 | H78: 63265 | I78: 64059 | J78: =I78 -> 64059 | K78: =J78 -> 64059 | L78: =K78 -> 64059 | M78: =L78 -> 64059 | N78: =M78 -> 64059 | O78: =N78 -> 64059
B79: Patrimônio Líquido | E79: 180986 | F79: 197058 | G79: 194894 | H79: 198325 | I79: 213720
B80: Total do Passivo + PL | E80: =SUM(E66:E79) -> 478130 | F80: =SUM(F66:F79) -> 499128 | G80: =SUM(G66:G79) -> 453387 | H80: =SUM(H66:H79) -> 455984 | I80: =SUM(I66:I79) -> 496325
B83: FCF
B85: EBIT | E85: =E35 -> 67766 | F85: =F35 -> 148282 | G85: =G35 -> 88710 | H85: =H35 -> 70706 | I85: =I35 -> 57029 | J85: =J35 -> 72991.128 | K85: =K35 -> 76604.56 | L85: =L35 -> 79099.082 | ... O85: =O35 -> 84668.153
B86: (-) IR | E86: =E40 -> -4627 | F86: =F40 -> -25320 | G86: =G40 -> -15185 | H86: =H40 -> -15000 | I86: =I40 -> -3793 | J86: =J40 -> -8358.8867 | K86: =K40 -> -8828.6328 | L86: =L40 -> -9152.9207 | ... O86: =O40 -> -9876.8999
B87: NOPAT | E87: =E85+E86 -> 63139 | F87: =F85+F86 -> 122962 | G87: =G85+G86 -> 73525 | H87: =H85+H86 -> 55706 | I87: =I85+I86 -> 53236 | J87: =J85+J86 -> 64632.242 | K87: =K85+K86 -> 67775.928 | L87: =L85+L86 -> 69946.161 | ... O87: =O85+O86 -> 74791.253
B88: (+) Depreciação e Amortização | E88: =-E33 -> 16597 | F88: =-F33 -> 16379 | G88: =-G33 -> 16379 | H88: =-H33 -> 15300 | I88: =-I33 -> 16525 | J88: =-J33 -> 16115.985 | K88: =-K33 -> 18088.472 | L88: =-L33 -> 20169.014 | ... O88: =-O33 -> 27119.803
B89: (-) Capex | E89: =-E19 -> -21720 | F89: =-F19 -> -27301 | G89: =-G19 -> -28184 | H89: =-H19 -> -29446 | I89: =-I19 -> -35098 | J89: =-J19 -> -37020.708 | K89: =-K19 -> -39048.744 | L89: =-L19 -> -41187.878 | ... O89: =-O19 -> -48334.415
B90: (+/-) Var. Capital de Giro | F90: =F91+F95 -> 23497 | G90: =G91+G95 -> -46758 | H90: =H91+H95 -> 18416 | I90: =I91+I95 -> -1048 | J90: =J91+J95 -> -18335.884 | K90: =K91+K95 -> -206.94058 | L90: =L91+L95 -> -2371.9275 | M90: =M91+M95 -> -1619.8529 | ... O90: =O91+O95 -> -1081.3747
B91: (-) Variação nos ativos | F91: =SUM(F92:F94) -> 11050 | G91: =SUM(G92:G94) -> -6546 | H91: =SUM(H92:H94) -> 13110 | I91: =SUM(I92:I94) -> 4660 | J91: =SUM(J92:J94) -> -16768.893 | K91: =SUM(K92:K94) -> -1355.728 | L91: =SUM(L92:L94) -> -3439.0234 | M91: =SUM(M92:M94) -> -2674.1436 | ... O91: =SUM(O92:O94) -> -2279.404
B92: (-) Contas a receber | F92: =-(F56-E56) -> 4104 | G92: =-(G56-F56) -> -697 | H92: =-(H56-G56) -> 2220 | I92: =-(I56-H56) -> 5717 | J92: =-(J56-I56) -> -4816.484 | K92: =-(K56-J56) -> -873.74178 | L92: =-(L56-K56) -> -811.60903 | M92: =-(M56-L56) -> -801.86972 | ... O92: =-(O56-N56) -> -911.19411
B93: (-) Estoque | F93: =-(F58-E58) -> -3326 | G93: =-(G58-F58) -> 1043 | H93: =-(H58-G58) -> 707 | I93: =-(I58-H58) -> -5834 | J93: =-(J58-I58) -> 3212.8136 | K93: =-(K58-J58) -> -1138.5084 | L93: =-(L58-K58) -> -1057.5478 | M93: =-(M58-L58) -> -1044.8572 | ... O93: =-(O58-N58) -> -1187.3098
B94: (-) Outros | F94: =-(F55-E55)+(F57-E57)+(F59-E59)+(F60-E60)+(F61-E61)+(F62-E62) -> 10272 | G94: =-(G55-F55)+(G57-F57)+(G59-F59)+(G60-F60)+(G61-F61)+(G62-F62) -> -6892 | H94: =-(H55-G55)+(H57-G57)+(H59-G59)+(H60-G60)+(H61-G61)+(H62-G62) -> 10183 | I94: =-(I55-H55)+(I57-H57)+(I59-H59)+(I60-H60)+(I61-H61)+(I62-H62) -> 4777 | J94: =-(J55-I55)+(J57-I57)+(J59-I59)+(J60-I60)+(J61-I61)+(J62-I62) -> -15165.222 | K94: =-(K55-J55)+(K57-J57)+(K59-J59)+(K60-J60)+(K61-J61)+(K62-J62) -> 656.52219 | L94: =-(L55-K55)+(L57-K57)+(L59-K59)+(L60-K60)+(L61-K61)+(L62-K62) -> -1569.8665 | M94: =-(M55-L55)+(M57-L57)+(M59-L59)+(M60-L60)+(M61-L61)+(M62-L62) -> -827.41668 | ... O94: =-(O55-N55)+(O57-N57)+(O59-N59)+(O60-N60)+(O61-N61)+(O62-N62) -> -180.90019
B95: (+) Variação nos Passivos | F95: =SUM(F96:F98) -> 12447 | G95: =SUM(G96:G98) -> -40212 | H95: =SUM(H96:H98) -> 5306 | I95: =SUM(I96:I98) -> -5708 | J95: =SUM(J96:J98) -> -1566.9912 | K95: =SUM(K96:K98) -> 1148.7874 | L95: =SUM(L96:L98) -> 1067.0958 | M95: =SUM(M96:M98) -> 1054.2907 | ... O95: =SUM(O96:O98) -> 1198.0294
B96: (+) Contas a pagar | F96: =(F66-E66) -> 1897 | G96: =(G66-F66) -> 3885 | H96: =(H66-G66) -> 2245 | I96: =(I66-H66) -> 694 | J96: =(J66-I66) -> -688.39118 | K96: =(K66-J66) -> 1148.7874 | L96: =(L66-K66) -> 1067.0958 | M96: =(M66-L66) -> 1054.2907 | ... O96: =(O66-N66) -> 1198.0294
B97: (+) Obrigações fiscais | F97: =(F69-E69)+(F70-E70)+(F76-E76) -> 7006 | G97: =(G69-F69)+(G70-F70)+(G76-F76) -> -13903 | H97: =(H69-G69)+(H70-G70)+(H76-G76) -> -528 | I97: =(I69-H69)+(I70-H70)+(I76-H76) -> -6251 | J97: =(J69-I69)+(J70-I70)+(J76-I76) -> 565.66667 | K97: =(K69-J69)+(K70-J70)+(K76-J76) -> 0 | L97: =(L69-K69)+(L70-K70)+(L76-K76) -> 0 | M97: =(M69-L69)+(M70-L70)+(M76-L76) -> 0 | ... O97: =(O69-N69)+(O70-N70)+(O76-N76) -> 0
B98: (+) Outros passivos | F98: =(F71-E71)+(F72-E72)+(F75-E75)+(F77-E77)+(F78-E78) -> 3544 | G98: =(G71-F71)+(G72-F72)+(G75-F75)+(G77-F77)+(G78-F78) -> -30194 | H98: =(H71-G71)+(H72-G72)+(H75-G75)+(H77-G77)+(H78-G78) -> 3589 | I98: =(I71-H71)+(I72-H72)+(I75-H75)+(I77-H77)+(I78-H78) -> -151 | J98: =(J71-I71)+(J72-I72)+(J75-I75)+(J77-I77)+(J78-I78) -> -1444.2667 | K98: =(K71-J71)+(K72-J72)+(K75-J75)+(K77-J77)+(K78-J78) -> 0 | L98: =(L71-K71)+(L72-K72)+(L75-K75)+(L77-K77)+(L78-K78) -> 0 | M98: =(M71-L71)+(M72-L72)+(M75-L75)+(M77-L77)+(M78-L78) -> 0 | ... O98: =(O71-N71)+(O72-N72)+(O75-N75)+(O77-N77)+(O78-N78) -> 0
B99: FREE CASH FLOW TO FIRM | F99: =SUM(F87:F90) -> 135537 | G99: =SUM(G87:G90) -> 14962 | H99: =SUM(H87:H90) -> 59976 | I99: =SUM(I87:I90) -> 33615 | J99: =SUM(J87:J90) -> 25391.634 | K99: =SUM(K87:K90) -> 46608.715 | L99: =SUM(L87:L90) -> 46555.37 | M99: =SUM(M87:M90) -> 48275.211 | ... O99: =SUM(O87:O90) -> 52495.266
B100: (+) Variação no endividamento | F100: =(F67+F74)-(E67+E74) -> -1179 | G100: =(G67+G74)-(F67+F74) -> -10579 | H100: =(H67+H74)-(G67+G74) -> -5955 | I100: =(I67+I74)-(H67+H74) -> 31223 | J100: =(J67+J74)-(I67+I74) -> -16938 | K100: =(K67+K74)-(J67+J74) -> -685.6 | L100: =(L67+L74)-(K67+K74) -> -586.92 | M100: =(M67+M74)-(L67+L74) -> 1411.496 | ... O100: =(O67+O74)-(N67+N74) -> -2782.8458
B101: (-) Resultado financeiro e não operacional | F101: =SUM(F36:F38) -> 10865 | G101: =SUM(G36:G38) -> 12994 | H101: =SUM(H36:H38) -> -15152 | I101: =SUM(I36:I38) -> -22805 | J101: =SUM(J36:J38) -> -8692 | K101: =SUM(K36:K38) -> -8692 | L101: =SUM(L36:L38) -> -8692 | M101: =SUM(M36:M38) -> -8692 | ... O101: =SUM(O36:O38) -> -8692
B102: (+) Ajuste de IR não operacional | F102: =F86 -> -25320 | G102: =G86 -> -15185 | H102: =H86 -> -15000 | I102: =I86 -> -3793 | J102: =J86 -> -8358.8867 | K102: =K86 -> -8828.6328 | L102: =L86 -> -9152.9207 | M102: =M86 -> -9306.7643 | ... O102: =O86 -> -9876.8999
B103: FREE CASH FLOW TO EQUITY | F103: =SUM(F99:F102) -> 119903 | G103: =SUM(G99:G102) -> 2192 | H103: =SUM(H99:H102) -> 23869 | I103: =SUM(I99:I102) -> 38240 | J103: =SUM(J99:J102) -> -8597.2523 | K103: =SUM(K99:K102) -> 28402.482 | L103: =SUM(L99:L102) -> 28123.529 | M103: =SUM(M99:M102) -> 31687.943 | ... O103: =SUM(O99:O102) -> 31143.521

Sheet Dados de Apoio para Gráficos
J1: Projetado
B2: Dados Financeiros | E2: 2020 | F2: 2021 | G2: 2022 | H2: 2023 | I2: 2024 | J2: 2025 | K2: 2026 | L2: 2027 | M2: 2028 | N2: 2029 | O2: 2030
B5: Premissas
B7: Receita minério de ferro (% Receita Líq.) | E7: =E16/'Dados Financeiros'!E24 -> 0.6913119 | F7: =F16/'Dados Financeiros'!F24 -> 0.70945476 | G7: =G16/'Dados Financeiros'!G24 -> 0.6433062 | H7: =H16/'Dados Financeiros'!H24 -> 0.66327992 | I7: =I16/'Dados Financeiros'!I24 -> 0.65209582
B8: Receita pelotas de minério de ferro (% Receita Líq.) | E8: =E17/'Dados Financeiros'!E24 -> 0.10695397 | F8: =F17/'Dados Financeiros'!F24 -> 0.12929437 | G8: =G17/'Dados Financeiros'!G24 -> 0.14238349 | H8: =H17/'Dados Financeiros'!H24 -> 0.13923947 | I8: =I17/'Dados Financeiros'!I24 -> 0.1548409
B9: Receita Outros minerais ferrosos (% Receita Líq.) | E9: =E18/'Dados Financeiros'!E24 -> 0.013799261 | F9: =F18/'Dados Financeiros'!F24 -> 0.010050285 | G9: =G18/'Dados Financeiros'!G24 -> 0.010706024 | H9: =H18/'Dados Financeiros'!H24 -> 0.012342238 | I9: =I18/'Dados Financeiros'!I24 -> 0.018921871
B10: Receita Níquel e outros produtos (% Receita Líq.) | E10: =E19/'Dados Financeiros'!E24 -> 0.12555677 | F10: =F19/'Dados Financeiros'!F24 -> 0.099303634 | G10: =G19/'Dados Financeiros'!G24 -> 0.15110283 | H10: =H19/'Dados Financeiros'!H24 -> 0.1250036 | I10: =I19/'Dados Financeiros'!I24 -> 0.096517075
B11: Receita cobre (% Receita Líq.) | E11: =E20/'Dados Financeiros'!E24 -> 0.055100001 | F11: =F20/'Dados Financeiros'!F24 -> 0.047617912 | G11: =G20/'Dados Financeiros'!G24 -> 0.040771187 | H11: =H20/'Dados Financeiros'!H24 -> 0.05688099 | I11: =I20/'Dados Financeiros'!I24 -> 0.073935099
B12: Receita outros (% Receita Líq.) | E12: =E21/'Dados Financeiros'!E24 -> 0.007278091 | F12: =F21/'Dados Financeiros'!F24 -> 0.0042790368 | G12: =G21/'Dados Financeiros'!G24 -> 0.01173027 | H12: =H21/'Dados Financeiros'!H24 -> 0.0032537752 | I12: =I21/'Dados Financeiros'!I24 -> 0.0036892308
B14: Receita Expandida
B16: Minério de Ferro | E16: 142478 | F16: 208242 | G16: 145714 | H16: 138006 | I16: 134335
B17: Pelotas de Minério de Ferro | E17: 22043 | F17: 37951 | G17: 32251 | H17: 28971 | I17: 31898
B18: Outros Minerais Ferrosos | E18: 2844 | F18: 2950 | G18: 2425 | H18: 2568 | I18: 3898
B19: Níquel e Outros | E19: 25877 | F19: 29148 | G19: 34226 | H19: 26009 | I19: 19883
B20: Cobre | E20: 11356 | F20: 13977 | G20: 9235 | H20: 11835 | I20: 15231
B21: Outros | E21: 1500 | F21: 1256 | G21: 2657 | H21: 677 | I21: 760
B23: Receita de vendas por área geográfica
B25: Américas (ex. EUA e Brasil) | G25: 6914 | H25: 6169 | I25: 5150
B26: EUA | G26: 8323 | H26: 8471 | I26: 5813
B27: Alemanha | G27: 11003 | H27: 7909 | I27: 8000
B28: Europa (ex. Alemanha) | G28: 25300 | H28: 19771 | I28: 16301
B29: Oriente Médio, África e Oceania | G29: 11600 | H29: 13663 | I29: 14299
B30: Japão | G30: 24399 | H30: 18239 | I30: 16466
B31: China | G31: 154067 | H31: 114960 | I31: 105200
B32: Ásia (ex. Japão e China) | G32: 24240 | H32: 16059 | I32: 15643
B33: Brasil | G33: 27678 | H33: 21267 | I33: 19133
B34: Receita Líquida | G34: =SUM(G25:G33) -> 293524 | H34: =SUM(H25:H33) -> 226508 | I34: =SUM(I25:I33) -> 206005
B36: CPV Expandido
B38: Pessoal
B39: Materiais e Serviços | G39: 9218 | H39: 9384 | I39: 14600
B40: Óleo combustível e gases | G40: 15705 | H40: 18797 | I40: 14907
B41: Manutenção | G41: 5472 | H41: 8446 | I41: 7523
B42: Royalties | G42: 15167 | H42: 16029 | I42: 24362
B43: Energia | G43: 7372 | H43: 6576 | I43: 6932
B44: Aquisição de minério de terceiros | G44: 3446 | H44: 3709 | I44: 3514
B45: Depreciação/Amortização | G45: 12214 | H45: 13247 | I45: 10745
B46: Frete | G46: 15430 | H46: 15753 | I46: 15689
B47: Outros | G47: 24744 | H47: 24494 | I47: 25832
B48: Total | G48: 8499 | H48: 7760 | I48: 7214
B50: Custos de Produção (US$/t)
B52: C1 | E52: 13.7 | F52: 17 | G52: 19.6 | H52: 22.3 | I52: 21.8
B53: All-in Minério de Ferro | G53: 49.3 | H53: 54.8 | I53: 55.9
B54: All-in Níquel | G54: 13440 | H54: 16854 | I54: 15420
B55: All-in Cobre | G55: 4502 | H55: 3437 | I55: 2616
B59: Receita Líquida | E59: ='Dados Financeiros'!E24 -> 206098 | F59: ='Dados Financeiros'!F24 -> 293524 | G59: ='Dados Financeiros'!G24 -> 226508 | H59: ='Dados Financeiros'!H24 -> 208066 | I59: ='Dados Financeiros'!I24 -> 206005
B60: Var. | F60: =F59/E59-1 -> 0.42419626 | G60: =G59/F59-1 -> -0.22831523 | H60: =H59/G59-1 -> -0.081418758 | I60: =I59/H59-1 -> -0.0099055108
B61: Preço Minério de Ferro | E61: =Macro!D9 -> 155.6 | F61: =Macro!E9 -> 121.05 | G61: =Macro!F9 -> 127.85 | H61: =Macro!G9 -> 131.05 | I61: =Macro!H9 -> 106.25 | L61: =E63*E61 -> 46742.24
B62: Var. | F62: =F61/E61-1 -> -0.2220437 | G62: =G61/F61-1 -> 0.056175134 | H62: =H61/G61-1 -> 0.025029331 | I62: =I61/H61-1 -> -0.18924075 | L62: =E63*E65 -> 4115.48
B63: Qntd. Produzida | E63: 300.4 | F63: 315.6 | G63: 308 | H63: 321 | I63: 328 | L63: =L61-L62 -> 42626.76
B64: Var. | F64: =F63/E63-1 -> 0.050599201 | G64: =G63/F63-1 -> -0.024081115 | H64: =H63/G63-1 -> 0.042207792 | I64: =I63/H63-1 -> 0.021806854
B65: C1 | E65: =E52 -> 13.7 | F65: =F52 -> 17 | G65: =G52 -> 19.6 | H65: =H52 -> 22.3 | I65: =I52 -> 21.8
B66: Var. | F66: =F65/E65-1 -> 0.24087591 | G66: =G65/F65-1 -> 0.15294118 | H66: =H65/G65-1 -> 0.1377551 | I66: =I65/H65-1 -> -0.022421525
B67: Lucro Líquido Minério de Ferro | E67: =(E63*E61)-(E63*E65) -> 42626.76 | F67: =(F63*F61)-(F63*F65) -> 32838.18 | G67: =(G63*G61)-(G63*G65) -> 33341 | H67: =(H63*H61)-(H63*H65) -> 34908.75 | I67: =(I63*I61)-(I63*I65) -> 27699.6

Sheet WACC
B2: WACC
B5: Custo de Capital
B6: TLR | D6: 0.1395 | I6: Valor de Mercado
B7: Beta | D7: 1.06 | I7: Market Cap | J7: 232578
B8: Prêmio de risco | D8: 0.06 | I8: (+) Dívida | J8: =D12 -> 91598
B9: Alíquota de Juros sobre o CP | D9: 0.41 | I9: (-) Caixa | J9: ='Dados Financeiros'!I54 -> 30671
B10: CAPM | D10: =(D6+(D7*D8)*(1-D9*15%)) -> 0.1991886 | I10: EV | J10: =J7+J8-J9 -> 293505
B12: Dívida Total | D12: ='Dados Financeiros'!I67+'Dados Financeiros'!I74 -> 91598
B13: Equity Total | D13: =J7 -> 232578
B15: D/(D+E) | D15: =D12/(D12+D13) -> 0.28255639
B16: E/(D+E) | D16: =D13/(D12+D13) -> 0.71744361
B17: D/E | D17: =D15/D16 -> 0.39383777
B19: Custo do Capital Próprio | D19: =D10 -> 0.1991886
B20: Custo do Capital de Terceiros antes do IR | D20: 0.1518
B21: Custo do Capital de Terceiros após o IR | D21: 0.1063
B23: WACC | D23: =(D19*D16)+(D21*D15) -> 0.17294233

Sheet Valuation
B2: DCF
B5: DCF
B7: Premissas
B8: IR | D8: ='Dados Financeiros'!J15 -> 0.13
B9: Taxa de Desconto | D9: =WACC!D23 -> 0.17294233
B10: Crescimento na Perpetuidade | D10: =Macro!N5 -> 0.04
B11: Múltiplo EV/EBITDA | D11: =WACC!J10/'Dados Financeiros'!I44 -> 3.6632718
B12: Data do Valuation | D12: 45827
B13: Data Final do Ano | D13: 46022
B14: Preço Atual | D14: 51.24
B15: Ações Negociadas | D15: 4539
B17: Fluxo de Caixa Descontado | D17: Entrada | E17: 2025 | F17: =+E17+1 -> 2026 | G17: =+F17+1 -> 2027 | H17: =+G17+1 -> 2028 | I17: =+H17+1 -> 2029 | J17: 2030 | K17: Saída | M17: Terminal Value
B18: Data | D18: =+D12 -> 45827 | E18: =DATE(YEAR($D$18)+E19,MONTH($D$13),DAY($D$13)) -> 46022 | F18: =DATE(YEAR($D$18)+F19,MONTH($D$13),DAY($D$13)) -> 46387 | G18: =DATE(YEAR($D$18)+G19,MONTH($D$13),DAY($D$13)) -> 46752 | H18: =DATE(YEAR($D$18)+H19,MONTH($D$13),DAY($D$13)) -> 47118 | I18: =DATE(YEAR($D$18)+I19,MONTH($D$13),DAY($D$13)) -> 47483 | J18: =DATE(YEAR($D$18)+J19,MONTH($D$13),DAY($D$13)) -> 47848 | K18: =J18 -> 47848 | M18: EV/EBITDA | N18: =+D11*('Dados Financeiros'!O35-'Dados Financeiros'!O33) -> 409509.67
B19: Período | F19: 1 | G19: =F19+1 -> 2 | H19: =G19+1 -> 3 | I19: =H19+1 -> 4 | J19: =I19+1 -> 5 | M19: Gordon | N19: =(J36*(1+D10))/(D9-D10) -> 383087
B20: Fração do ano | E20: =YEARFRAC(D18,E18) -> 0.53333333 | F20: =YEARFRAC(E18,F18) -> 1 | G20: =YEARFRAC(F18,G18) -> 1 | H20: =YEARFRAC(G18,H18) -> 1 | I20: =YEARFRAC(H18,I18) -> 1 | J20: =YEARFRAC(I18,J18) -> 1 | M20: Média | N20: =AVERAGE(N18:N19) -> 396298.33
B22: EBIT | E22: 89107.113 | F22: 94693.032 | G22: 99268.096 | H22: 102646.02 | I22: 107291.63 | J22: 111787.96
B23: (-) IR | E23: -10453.965 | F23: -11180.134 | G23: -11774.892 | H23: -12214.023 | I23: -12817.952 | J23: -13402.474
B24: NOPAT | E24: 78653.148 | F24: 83512.898 | G24: 87493.203 | H24: 90432.001 | I24: 94473.682 | J24: 98385.482
B25: (+) Depreciação e Amortização | E25: 0 | F25: 0 | G25: 0 | H25: 0 | I25: 0 | J25: 0
B26: (-) Capex | E26: -37020.708 | F26: -39048.744 | G26: -41187.878 | H26: -43444.196 | I26: -45824.118 | J26: -48334.415
B27: (+/-) Var. Capital de Giro | E27: -18335.884 | F27: -206.94058 | G27: -2371.9275 | H27: -1619.8529 | I27: 408.58079 | J27: -1081.3747
B28: (-) Variação nos ativos | E28: -16768.893 | F28: -1355.728 | G28: -3439.0234 | H28: -2674.1436 | I28: -743.37052 | J28: -2279.404
B29: (-) Contas a receber | E29: -4816.484 | F29: -873.74178 | G29: -811.60903 | H29: -801.86972 | I29: -876.14818 | J29: -911.19411
B30: (-) Estoque | E30: 3212.8136 | F30: -1138.5084 | G30: -1057.5478 | H30: -1044.8572 | I30: -1141.644 | J30: -1187.3098
B31: (-) Outros | E31: -15165.222 | F31: 656.52219 | G31: -1569.8665 | H31: -827.41668 | I31: 1274.4216 | J31: -180.90019
B32: (+) Variação nos Passivos | E32: -1566.9912 | F32: 1148.7874 | G32: 1067.0958 | H32: 1054.2907 | I32: 1151.9513 | J32: 1198.0294
B33: (+) Contas a pagar | E33: -688.39118 | F33: 1148.7874 | G33: 1067.0958 | H33: 1054.2907 | I33: 1151.9513 | J33: 1198.0294
... B35: (+) Outros passivos | E35: -1444.2667 | F35: 0 | G35: 0 | H35: 0 | I35: 0 | J35: 0
B36: FREE CASH FLOW TO FIRM | E36: 23296.556 | F36: 44257.213 | G36: 43933.398 | H36: 45367.952 | I36: 49058.145 | J36: 48969.692 | K36: =N20 -> 396298.33
B38: FCFF sensibilizado pelo período | D38: 0 | E38: =+E36*E20 -> 12424.83 | F38: =F36*F20 -> 44257.213 | G38: =G36*G20 -> 43933.398 | H38: =H36*H20 -> 45367.952 | I38: =I36*I20 -> 49058.145 | J38: =J36*J20 -> 48969.692 | K38: =K36 -> 396298.33
B40: TIR FCFF | E40: =E38 -> 12424.83 | F40: =F38 -> 44257.213 | G40: =G38 -> 43933.398 | H40: =H38 -> 45367.952 | I40: =I38 -> 49058.145 | J40: =J38 -> 48969.692 | K40: =K38 -> 396298.33
B42: Valor Intrínseco
B44: Enterprise Value | D44: =XNPV(D9,D38:K38,D18:K18) -> 309073.34
B45: (+) Caixa | D45: ='Dados Financeiros'!I54 -> 30671
B46: (-) Dívida | D46: =WACC!J8 -> 91598 | I46: Sensitivity Analysis
B47: Equity Value | D47: =D44+D45-D46 -> 248146.34 | H47: WACC
G48: g | H48: =D49 -> 54.669825 | I48: =J48+1% -> 0.1929 | J48: =K48+1% -> 0.1829 | K48: 0.1729 | L48: =K48-2% -> 0.1529 | M48: =L48-2% -> 0.1329
B49: Equity/Ação | D49: =D47/D15 -> 54.669825 | H49: =H50-0.5% -> 0.03 | I49: 46.801775 | J49: 49.891425 | K49: 53.30847 | L49: 61.39958 | M49: 71.879328
B50: Upside | D50: =D49/D14-1 -> 0.066936482 | H50: =H51-0.5% -> 0.035 | I50: 47.27281 | J50: 50.448056 | K50: 53.972327 | L50: 62.375678 | M50: 73.399325
H51: 0.04 | I51: 47.774651 | J51: 51.04364 | K51: 54.686136 | L51: 63.438234 | M51: 75.082938
H52: =H51+0.5% -> 0.045 | I52: 48.310423 | J52: 51.682413 | K52: 55.455755 | L52: 64.599265 | M52: 76.958089
H53: =H52+0.5% -> 0.05 | I53: 48.883688 | J53: 52.36925 | K53: 56.287995 | L53: 65.873128 | M53: 79.059434
