Workbook
Name Case_Cell: [1]Inputs!$F$9
Name Case_Number: [1]Inputs!$E$9
Name Company_Name: [1]Inputs!$E$4
Name Comps_Range: '[1]Public-Comps-Data'!$D$2:$AA$106
Name Days_in_Year: [1]Inputs!$E$14
Name Equity_Interest_Value: '[1]YHOO-Equity-Interests'!$E$24
Name Forward_Year_1: [1]Inputs!$L$13
Name Forward_Year_2: [1]Inputs!$L$14
Name Forward_Year_3: [1]Inputs!$L$15
Name FYear_1_Name: [1]Inputs!$I$13
Name FYear_2_Name: [1]Inputs!$I$14
Name Hist_Year: [1]Inputs!$E$6
Name MA_Comps_Range: '[1]M&A-Comps-Data'!$D$2:$AK$84
Name Q4_Stub: [1]DCF!$P$4
Name Tax_Rate: [1]Inputs!$L$4
Name Ticker: [1]Inputs!$E$5
Name TTM: [1]Inputs!$L$12
Name Units: [1]Inputs!$E$15
Name WACC: #REF!
Name x: [2]Inputs!$L$12

Sheet Histórico
E2: Histórico | F2: Histórico | G2: Histórico | H2: Histórico
D3: Unit | E3: 2015 | F3: 2016 | G3: 2017 | H3: 2018
B4: DEMONSTRATIVO DE RESULTADOS
C5: Receita Bruta | D5: [R$] | E5: 249785250 | F5: 3.1389056e+08 | G5: 3.5301393e+08 | H5: 4.1868751e+08
C6: # produtos vendidos | D6: [#] | E6: 121550 | F6: 146870 | G6: 154370 | H6: 174370
C8: Deduções | D8: [R$] | E8: -60114984 | F8: -76149851 | G8: -83452494 | H8: -1.0062457e+08
C9: Impostos sobre as vendas | D9: [R$] | E9: -58449748 | F9: -74580398 | G9: -81334410 | H9: -97972878
C10: Devoluções | D10: [R$] | E10: -1665235 | F10: -1569452.8 | G10: -2118083.6 | H10: -2651687.6
C12: Receita Líquida | D12: [R$] | E12: 1.8967027e+08 | F12: 2.3774071e+08 | G12: 2.6956144e+08 | H12: 3.1806295e+08
C14: Custo dos produtos vendidos | D14: [R$] | E14: -1.4924686e+08 | F14: -1.8176446e+08 | G14: -2.0878504e+08 | H14: -2.4609444e+08
E15: 0.98
C16: Custo produtos | D16: [R$] | E16: -1.4322686e+08 | F16: -1.7408371e+08 | G16: -2.0075902e+08 | H16: -2.363491e+08
C17: Pessoal | D17: [R$] | E17: -6020000 | F17: -7680750 | G17: -8026018 | H17: -9745335.6
C18: # funcionários | D18: [#] | E18: 172 | F18: 210 | G18: 211 | H18: 244
C20: Lucro Bruto | D20: [R$] | E20: 40423404 | F20: 55976256 | G20: 60776398 | H20: 71968511
C22: Despesas Operacionais (SG&A) | D22: [R$] | E22: -19277517 | F22: -22537634 | G22: -26102116 | H22: -29072444
C24: Despesas comerciais | D24: [R$] | E24: -10441128 | F24: -13126312 | G24: -16031489 | H24: -18181382
C25: Pessoal | D25: [R$] | E25: -2448000 | F25: -3144592 | G25: -3428891.7 | H25: -3987875.6
C26: # funcionários | D26: [#] | E26: 36 | F26: 44 | G26: 46 | H26: 51
C27: Comissões | D27: [R$] | E27: -4745919.8 | F27: -5650030.2 | G27: -7413292.6 | H27: -8373750.3
C28: Marketing | D28: [R$] | E28: -2747637.8 | F28: -3766686.8 | G28: -4659783.9 | H28: -5233593.9
C29: Outros | D29: [R$] | E29: -499570.5 | F29: -565003.02 | G29: -529520.9 | H29: -586162.52
C31: Despesas gerais e administrativas | D31: [R$] | E31: -8836389.4 | F31: -9411322.1 | G31: -10070627 | H31: -10891061
... C49: Resultado não-operacional | D49: [R$] | E49: 0 | F49: -1242590 | G49: -227000 | H49: -150000
C50: Outras receitas | D50: [R$] | G50: 200000 | H50: 45000
C51: Outras despesas | D51: [R$] | E51: 0 | F51: -1242590 | G51: -427000 | H51: -195000
C53: LAIR | D53: [R$] | E53: 12775555 | F53: 18724623 | G53: 23351788 | H53: 32679864
C54: IR/CSLL | D54: [R$] | E54: -4265757.7 | F54: -6263386.2 | G54: -7846200.7 | H54: -11045794
C56: Lucro Líquido | D56: [R$] | E56: 8509797 | F56: 12461236 | G56: 15505587 | H56: 21634070
D59: Unit | E59: 2015 | F59: 2016 | G59: 2017 | H59: 2018
B60: BALANÇO PATRIMONIAL
C61: ATIVO | D61: [R$] | E61: 1.0009875e+08 | F61: 1.4312784e+08 | G61: 1.4408256e+08 | H61: 1.5614796e+08
C62: ATVO CIRCULANTE | D62: [R$] | E62: 74008987 | F62: 1.1859014e+08 | G62: 1.1956703e+08 | H62: 1.3096122e+08
C63: Caixa e equivalentes | D63: [R$] | E63: 2529062 | F63: 25688122 | G63: 16852498 | H63: 9115958.5
C64: Contas a receber | D64: [R$] | E64: 47875506 | F64: 61295852 | G64: 67661004 | H64: 82574482
C65: Estoque | D65: [R$] | E65: 23075439 | F65: 30948215 | G65: 34575165 | H65: 38734992
C66: Outros | D66: [R$] | E66: 528980 | F66: 657956 | G66: 478362 | H66: 535791
C68: ATIVO NÃO CIRCULANTE | D68: [R$] | E68: 26089767 | F68: 24537700 | G68: 24515531 | H68: 25186741
C69: Imobilizado | D69: [R$] | E69: 42977454 | F69: 45771081 | G69: 50536769 | H69: 56440263
C70: (-) Depreciação acumulada | D70: [R$] | E70: -17190982 | F70: -21628409 | G70: -26443801 | H70: -31792653
C71: Intangível | D71: [R$] | E71: 388839.41 | F71: 577173.75 | G71: 736030.02 | H71: 1029111.3
C72: (-) Amortização acumulada | D72: [R$] | E72: -85544.671 | F72: -182145.99 | G72: -313466.36 | H72: -489980.49
C74: PASSIVO | D74: [R$] | E74: 1.0009875e+08 | F74: 1.4312784e+08 | G74: 1.4408256e+08 | H74: 1.5614796e+08
... C87: Lucros/prejuízos acumulados | D87: [R$] | E87: 11123099 | F87: 19084335 | G87: 25089922 | H87: 37723992

Sheet WACC
A2: Company Comp Set
A3: Company Name | B3: 5 Year Beta (Beta alavancado) | C3: Tax Rate Imp. Renda (T) | D3: Debt/Equity % (D/E) | E3: Beta desalavancado
A4: EMPRESA A | B4: 1.2334984 | C4: 0.275 | D4: 0.55187359 | E4: =B4/(1+(D4)*(1-C4)) -> 0.88100212
A5: SCHNEIDER ELECTRIC SE | B5: 1.144376 | C5: 0.28611221 | D5: 0.36527382 | E5: =B5/(1+(D5)*(1-C5)) -> 0.90768416
A6: TOSHIBA CORP | B6: 1.0769046 | C6: 0.4 | D6: 2.1443166 | E6: =B6/(1+(D6)*(1-C6)) -> 0.47096532
A7: ITRON INC | B7: 1.0426642 | C7: 0.58579414 | D7: 0.46824265 | E7: =B7/(1+(D7)*(1-C7)) -> 0.8732905
A8: XYLEM INC | B8: 1.0804727 | C8: 0.23529411 | D8: 1.0729497 | E8: =B8/(1+(D8)*(1-C8)) -> 0.59350625
A9: ORACLE CORP | B9: 1.0527772 | C9: 0.22207657 | D9: 0.9176606 | E9: =B9/(1+(D9)*(1-C9)) -> 0.61426909
A10: HONEYWELL INTERNATIONAL INC | B10: 1.0763 | C10: 0.24845009 | D10: 0.80690536 | E10: =B10/(1+(D10)*(1-C10)) -> 0.66999512
A11: ABB LTD-REG | B11: 1.0218681 | C11: 0.27902822 | D11: 0.48953011 | E11: =B11/(1+(D11)*(1-C11)) -> 0.75529596
A12: MACQUARIE INFRASTRUCTURE COR | B12: 0.89746911 | C12: 0.31512077 | D12: 0.97853813 | E12: =B12/(1+(D12)*(1-C12)) -> 0.5373486
A13: HERKULES SA | B13: 0.82393318 | C13: 0.4 | D13: 0.43432564 | E13: =B13/(1+(D13)*(1-C13)) -> 0.65360638
A14: ESCO TECHNOLOGIES INC | B14: 0.9852408 | C14: 0.32940662 | D14: 0.17883009 | E14: =B14/(1+(D14)*(1-C14)) -> 0.87974033
A15: SIEMENS AG-REG | B15: 0.88617576 | C15: 0.27120476 | D15: 0.97776886 | E15: =B15/(1+(D15)*(1-C15)) -> 0.5174467
A17: Summary Statistics | B17: =B3 -> 5 Year Beta (Beta alavancado) | C17: =C3 -> Tax Rate Imp. Renda (T) | D17: =D3 -> Debt/Equity % (D/E) | E17: =E3 -> Beta desalavancado
A18: Média | B18: =AVERAGE(B4:B15) -> 1.0268067 | C18: =AVERAGE(C4:C15) -> 0.32062396 | D18: =AVERAGE(D4:D15) -> 0.78218459 | E18: =AVERAGE(E4:E15) -> 0.69617921
A20: Company Name | B20: Debt/Equity % (D/E) | C20: Tax Rate Imp. Renda (T) | D20: Beta desalavancado | E20: Beta realavancado
A21: Company Elektric | B21: =(Model!H119+Model!H123)/Model!H125 -> 0.44152202 | C21: 0.34 | D21: =E18 -> 0.69617921 | E21: =D21*(1+B21*(1-C21)) -> 0.89904899
A24: CAPM (Rf + B*(Rm - Rf) + Rs + Rp
A25: Risk Free (T-Bond) | B25: 0.0258 | C25: Taxa livre de risco
A26: Beta Elektric | B26: =E21 -> 0.89904899
A27: Equity Risk Premium (Rm - Rf) - USA | B27: 0.0549 | C27: Prêmio de risco de mercado
A28: BR Country Risk (Embi+) | B28: 0.0253 | C28: Risco país
A29: Liquidity Premium | B29: 0.03 | C29: Risco pela falta de liquidez quando comparada a empresas de capital aberto
A30: CAPM [Target.Co] - nominal USD | B30: =B25+B26*B27+B28+B29 -> 0.13045779
A32: CPI (Inflação projetada nos EUA) | B32: 0.021
A33: CAPM [Target.Co] - real USD | B33: =(1+B30)/(1+B32)-1 -> 0.10720645
A35: IPCA (Inflação projetada em BRL) | B35: 0.04
A36: CAPM [Target.Co] - BRL nominal | B36: =(1+B33)*(1+B35)-1 -> 0.15149471
A38: WACC [Target.Co] [(Ke x %Capital Próprio) + (Kd x % Capital de Terceiros)]
A39: Dívida Total - BRLmm | B39: =Model!H119+Model!H123 -> 34316854
A40: Equity Total - BRLmm | B40: =Model!H125 -> 77723992
A42: D / (D+E) | B42: =B39/(B39+B40) -> 0.30628878 | C42: % capital de terceiros (debt)
A43: E / (D+E) | B43: =B40/(B39+B40) -> 0.69371122 | C43: % capital próprio (equity)
A45: Kd | B45: 0.14
A46: Kd com Benefício Fiscal | B46: =B45*(1-C21) -> 0.0924
A48: WACC YoY nominal - BRL | B48: =B36*B43+B46*B42 -> 0.13339466

Sheet Model
E1: PROJETO ELEKTRIC
E2: Histórico | I2: Projeções
D3: Unit | E3: 2015 | F3: =E3+1 -> 2016 | G3: =F3+1 -> 2017 | H3: =G3+1 -> 2018 | I3: 2019E | J3: 2020E | K3: 2021E | L3: 2022E | M3: 2023E | N3: 2024E | O3: 2025E | P3: 2026E | R3: CAGR 16-24
B4: DEMONSTRATIVO DO RESULTADO
C5: Receita Bruta | D5: [R$] | E5: =Histórico!E5 -> 249785250 | F5: =Histórico!F5 -> 3.1389056e+08 | G5: =Histórico!G5 -> 3.5301393e+08 | H5: =Histórico!H5 -> 4.1868751e+08 | I5: =I8*I10 -> 4.8537881e+08 | J5: =J8*J10 -> 5.5673552e+08 | K5: =K8*K10 -> 6.2762223e+08 | L5: =L8*L10 -> 7.032891e+08 | M5: =M8*M10 -> 7.7524105e+08 | N5: =N8*N10 -> 8.4270926e+08 | O5: =O8*O10 -> 9.0801505e+08 | P5: =P8*P10 -> 9.706247e+08 | R5: =(#REF!/H5)^(1/8)-1 -> #REF!
C6: % crescimento | D6: [%] | F6: =F5/E5-1 -> 0.25664171 | G6: =G5/F5-1 -> 0.12464016 | H6: =H5/G5-1 -> 0.18603679 | I6: =I5/H5-1 -> 0.15928657 | J6: =J5/I5-1 -> 0.1470124 | K6: =K5/J5-1 -> 0.12732565 | L6: =L5/K5-1 -> 0.12056117 | M6: =M5/L5-1 -> 0.10230778 | ... P6: =P5/O5-1 -> 0.068952222
C8: # produtos vendidos | D8: [#] | E8: =Histórico!E6 -> 121550 | F8: =Histórico!F6 -> 146870 | G8: =Histórico!G6 -> 154370 | H8: =Histórico!H6 -> 174370 | I8: =H8+I9 -> 194370 | J8: =I8+J9 -> 214370 | K8: =J8+K9 -> 232370 | L8: =K8+L9 -> 250370 | M8: =L8+M9 -> 265370 | N8: =M8+N9 -> 277370 | O8: =N8+O9 -> 287370 | P8: =O8+P9 -> 295370
C9: Aumento de unidades vendidas | D9: [#] | F9: =F8-E8 -> 25320 | G9: =G8-F8 -> 7500 | H9: =H8-G8 -> 20000 | I9: 20000 | J9: 20000 | K9: 18000 | L9: 18000 | M9: 15000 | N9: 12000 | O9: 10000 | P9: 8000
C10: Preço médio | D10: [R$/unidade] | E10: =E5/E8 -> 2055 | F10: =F5/F8 -> 2137.2 | G10: =G5/G8 -> 2286.804 | H10: =H5/H8 -> 2401.1442 | I10: =H10*(1+I11) -> 2497.19 | J10: =I10*(1+J11) -> 2597.0776 | K10: =J10*(1+K11) -> 2700.9607 | L10: =K10*(1+L11) -> 2808.9991 | M10: =L10*(1+M11) -> 2921.3591 | N10: =M10*(1+N11) -> 3038.2134 | O10: =N10*(1+O11) -> 3159.742 | P10: =O10*(1+P11) -> 3286.1316
C11: Variação no preço médio | D11: [%] | F11: =F10/E10-1 -> 0.04 | G11: =G10/F10-1 -> 0.07 | H11: =H10/G10-1 -> 0.05 | I11: 0.04 | J11: =I11 -> 0.04 | K11: =J11 -> 0.04 | L11: =K11 -> 0.04 | M11: =L11 -> 0.04 | N11: =M11 -> 0.04 | O11: =N11 -> 0.04 | P11: =O11 -> 0.04
C13: Deduções | D13: [R$] | E13: =E15+E17 -> -60114984 | F13: =F15+F17 -> -76149851 | G13: =G15+G17 -> -83452494 | H13: =H15+H17 -> -1.0062457e+08 | I13: =I15+I17 -> -1.1665271e+08 | J13: =J15+J17 -> -1.338021e+08 | K13: =K15+K17 -> -1.5083854e+08 | L13: =L15+L17 -> -1.6902381e+08 | ... P13: =P15+P17 -> -2.3327347e+08
C14: % receita bruta | D14: [%] | E14: =E13/E$5 -> -0.24066667 | F14: =F13/F$5 -> -0.2426 | G14: =G13/G$5 -> -0.2364 | H14: =H13/H$5 -> -0.24033333 | I14: =I13/I$5 -> -0.24033333 | J14: =J13/J$5 -> -0.24033333 | K14: =K13/K$5 -> -0.24033333 | L14: =L13/L$5 -> -0.24033333 | ... P14: =P13/P$5 -> -0.24033333
C15: Impostos sobre as vendas | D15: [R$] | E15: =Histórico!E9 -> -58449748 | F15: =Histórico!F9 -> -74580398 | G15: =Histórico!G9 -> -81334410 | H15: =Histórico!H9 -> -97972878 | I15: =I$5*I16 -> -1.1357864e+08 | J15: =J$5*J16 -> -1.3027611e+08 | K15: =K$5*K16 -> -1.468636e+08 | L15: =L$5*L16 -> -1.6456965e+08 | M15: =M$5*M16 -> -1.8140641e+08 | N15: =N$5*N16 -> -1.9719397e+08 | O15: =O$5*O16 -> -2.1247552e+08 | P15: =P$5*P16 -> -2.2712618e+08
C16: % receita bruta | D16: [%] | E16: =E15/E$5 -> -0.234 | F16: =F15/F$5 -> -0.2376 | G16: =G15/G$5 -> -0.2304 | H16: =H15/H$5 -> -0.234 | I16: =H16 -> -0.234 | J16: =I16 -> -0.234 | K16: =J16 -> -0.234 | L16: =K16 -> -0.234 | M16: =L16 -> -0.234 | N16: =M16 -> -0.234 | O16: =N16 -> -0.234 | P16: =O16 -> -0.234
C17: Devoluções | D17: [R$] | E17: =Histórico!E10 -> -1665235 | F17: =Histórico!F10 -> -1569452.8 | G17: =Histórico!G10 -> -2118083.6 | H17: =Histórico!H10 -> -2651687.6 | I17: =I$5*I18 -> -3074065.8 | J17: =J$5*J18 -> -3525991.6 | K17: =K$5*K18 -> -3974940.8 | L17: =L$5*L18 -> -4454164.3 | M17: =M$5*M18 -> -4909860 | N17: =N$5*N18 -> -5337158.6 | O17: =O$5*O18 -> -5750762 | P17: =P$5*P18 -> -6147289.8
C18: % receita bruta | D18: [%] | E18: =E17/E$5 -> -0.0066666667 | F18: =F17/F$5 -> -0.005 | G18: =G17/G$5 -> -0.006 | H18: =H17/H$5 -> -0.0063333333 | I18: =H18 -> -0.0063333333 | J18: =I18 -> -0.0063333333 | K18: =J18 -> -0.0063333333 | L18: =K18 -> -0.0063333333 | M18: =L18 -> -0.0063333333 | N18: =M18 -> -0.0063333333 | O18: =N18 -> -0.0063333333 | P18: =O18 -> -0.0063333333
C20: Receita líquida | D20: [R$] | E20: =E5+E13 -> 1.8967027e+08 | F20: =F5+F13 -> 2.3774071e+08 | G20: =G5+G13 -> 2.6956144e+08 | H20: =H5+H13 -> 3.1806295e+08 | I20: =I5+I13 -> 3.6872611e+08 | J20: =J5+J13 -> 4.2293342e+08 | K20: =K5+K13 -> 4.7678369e+08 | L20: =L5+L13 -> 5.3426529e+08 | ... P20: =P5+P13 -> 7.3735123e+08
C21: % receita bruta | D21: [%] | E21: =E20/E$5 -> 0.75933333 | F21: =F20/F$5 -> 0.7574 | G21: =G20/G$5 -> 0.7636 | H21: =H20/H$5 -> 0.75966667 | I21: =I20/I$5 -> 0.75966667 | J21: =J20/J$5 -> 0.75966667 | K21: =K20/K$5 -> 0.75966667 | L21: =L20/L$5 -> 0.75966667 | ... P21: =P20/P$5 -> 0.75966667
C23: Custos operacionais | D23: [R$] | E23: =E26+E28 -> -1.4924686e+08 | F23: =F26+F28 -> -1.8176446e+08 | G23: =G26+G28 -> -2.0878504e+08 | H23: =H26+H28 -> -2.4609444e+08 | I23: =I26+I28 -> -2.8521146e+08 | J23: =J26+J28 -> -3.270641e+08 | K23: =K26+K28 -> -3.6857952e+08 | L23: =L26+L28 -> -4.1293959e+08 | ... P23: =P26+P28 -> -5.6945389e+08
C24: % receita bruta | D24: [%] | E24: =E23/E$5 -> -0.5975007 | F24: =F23/F$5 -> -0.57906952 | G24: =G23/G$5 -> -0.5914357 | H24: =H23/H$5 -> -0.58777592 | I24: =I23/I$5 -> -0.58760592 | J24: =J23/J$5 -> -0.58746764 | K24: =K23/K$5 -> -0.58726333 | L24: =L23/L$5 -> -0.58715483 | ... P24: =P23/P$5 -> -0.58668802
C26: COGS | D26: [R$] | E26: =Histórico!E16 -> -1.4322686e+08 | F26: =Histórico!F16 -> -1.7408371e+08 | G26: =Histórico!G16 -> -2.0075902e+08 | H26: =Histórico!H16 -> -2.363491e+08 | I26: =I$5*I27 -> -2.7399634e+08 | J26: =J$5*J27 -> -3.142772e+08 | K26: =K$5*K27 -> -3.5429275e+08 | L26: =L$5*L27 -> -3.970067e+08 | M26: =M$5*M27 -> -4.3762357e+08 | N26: =N$5*N27 -> -4.7570938e+08 | O26: =O$5*O27 -> -5.1257449e+08 | P26: =P$5*P27 -> -5.4791764e+08
C27: % receita bruta | D27: [%] | E27: =E26/E$5 -> -0.5734 | F27: =F26/F$5 -> -0.5546 | G27: =G26/G$5 -> -0.5687 | H27: =H26/H$5 -> -0.5645 | I27: =H27 -> -0.5645 | J27: =I27 -> -0.5645 | K27: =J27 -> -0.5645 | L27: =K27 -> -0.5645 | M27: =L27 -> -0.5645 | N27: =M27 -> -0.5645 | O27: =N27 -> -0.5645 | P27: =O27 -> -0.5645
C28: Pessoal | D28: [R$] | E28: =Histórico!E17 -> -6020000 | F28: =Histórico!F17 -> -7680750 | G28: =Histórico!G17 -> -8026018 | H28: =Histórico!H17 -> -9745335.6 | I28: =I30*I32 -> -11215124 | J28: =J30*J32 -> -12786903 | K28: =K30*K32 -> -14286772 | L28: =L30*L32 -> -15932896 | M28: =M30*M32 -> -17444885 | N28: =N30*N32 -> -18799658 | O28: =O30*O32 -> -20129784 | P28: =P30*P32 -> -21536241
C29: % receita bruta | D29: [%] | E29: =E28/E$5 -> -0.024100703 | F29: =F28/F$5 -> -0.024469515 | G29: =G28/G$5 -> -0.022735697 | H29: =H28/H$5 -> -0.023275916 | I29: =I28/I$5 -> -0.02310592 | J29: =J28/J$5 -> -0.022967643 | K29: =K28/K$5 -> -0.02276333 | L29: =L28/L$5 -> -0.022654831 | ... P29: =P28/P$5 -> -0.022188021
C30: # funcionários | D30: [#] | E30: =Histórico!E18 -> 172 | F30: =Histórico!F18 -> 210 | G30: =Histórico!G18 -> 211 | H30: =Histórico!H18 -> 244 | I30: =ROUND(I8/I31,0) -> 270 | J30: =ROUND(J8/J31,0) -> 296 | K30: =ROUND(K8/K31,0) -> 318 | L30: =ROUND(L8/L31,0) -> 341 | M30: =ROUND(M8/M31,0) -> 359 | N30: =ROUND(N8/N31,0) -> 372 | O30: =ROUND(O8/O31,0) -> 383 | P30: =ROUND(P8/P31,0) -> 394
C31: Qtd produzida / func. | D31: [#] | E31: =E8/E30 -> 706.68605 | F31: =F8/F30 -> 699.38095 | G31: =G8/G30 -> 731.61137 | H31: =H8/H30 -> 714.63115 | I31: 720 | J31: 725 | K31: 730 | L31: 735 | M31: 740 | N31: 745 | O31: 750 | P31: =O31 -> 750
C32: Custo médio / funcionário | D32: [R$ / FTE] | E32: =E28/E30 -> -35000 | F32: =F28/F30 -> -36575 | G32: =G28/G30 -> -38038 | H32: =H28/H30 -> -39939.9 | I32: =H32*(1+I33) -> -41537.496 | J32: =I32*(1+J33) -> -43198.996 | K32: =J32*(1+K33) -> -44926.956 | L32: =K32*(1+L33) -> -46724.034 | M32: =L32*(1+M33) -> -48592.995 | N32: =M32*(1+N33) -> -50536.715 | O32: =N32*(1+O33) -> -52558.184 | P32: =O32*(1+P33) -> -54660.511
C33: Crescimento custo médio / func. | D33: [%] | F33: =F32/E32-1 -> 0.045 | G33: =G32/F32-1 -> 0.04 | H33: =H32/G32-1 -> 0.05 | I33: 0.04 | J33: =I33 -> 0.04 | K33: =J33 -> 0.04 | L33: =K33 -> 0.04 | M33: =L33 -> 0.04 | N33: =M33 -> 0.04 | O33: =N33 -> 0.04 | P33: =O33 -> 0.04
C35: Lucro Bruto | D35: [R$] | E35: =E20+E23 -> 40423404 | F35: =F20+F23 -> 55976256 | G35: =G20+G23 -> 60776398 | H35: =H20+H23 -> 71968511 | I35: =I20+I23 -> 83514641 | J35: =J20+J23 -> 95869312 | K35: =K20+K23 -> 1.0820417e+08 | L35: =L20+L23 -> 1.2132569e+08 | ... P35: =P20+P23 -> 1.6789735e+08
C36: Margem bruta | D36: [%] | E36: =E35/E$20 -> 0.21312462 | F36: =F35/F$20 -> 0.23545086 | G36: =G35/G$20 -> 0.22546399 | H36: =H35/H$20 -> 0.22627128 | I36: =I35/I$20 -> 0.22649506 | J36: =J35/J$20 -> 0.22667708 | K36: =K35/K$20 -> 0.22694603 | L36: =L35/L$20 -> 0.22708886 | ... P36: =P35/P$20 -> 0.22770335
C38: Despesas Operacionais (SG&A) | D38: [R$] | E38: =E41+E56 -> -19277517 | F38: =F41+F56 -> -22537634 | G38: =G41+G56 -> -26102116 | H38: =H41+H56 -> -29072444 | I38: =I41+I56 -> -32335043 | J38: =J41+J56 -> -35812134 | K38: =K41+K56 -> -39530627 | L38: =L41+L56 -> -43191805 | ... P38: =P41+P56 -> -57093455
C39: % receita bruta | D39: [%] | E39: =E38/E$5 -> -0.077176364 | F39: =F38/F$5 -> -0.071800929 | G39: =G38/G$5 -> -0.073940752 | H39: =H38/H$5 -> -0.069437092 | I39: =I38/I$5 -> -0.066618159 | J39: =J38/J$5 -> -0.06432522 | K39: =K38/K$5 -> -0.062984746 | L39: =L38/L$5 -> -0.061414011 | ... P39: =P38/P$5 -> -0.058821349
C41: Despesas comerciais | D41: [R$] | E41: =SUM(E43,E49,E51,E53) -> -10441128 | F41: =SUM(F43,F49,F51,F53) -> -13126312 | G41: =SUM(G43,G49,G51,G53) -> -16031489 | H41: =SUM(H43,H49,H51,H53) -> -18181382 | I41: =SUM(I43,I49,I51,I53) -> -21008339 | J41: =SUM(J43,J49,J51,J53) -> -24032363 | K41: =SUM(K43,K49,K51,K53) -> -27081569 | L41: =SUM(L43,L49,L51,L53) -> -30244785 | ... P41: =SUM(P43,P49,P51,P53) -> -41465249
C42: % receita bruta | D42: [%] | E42: =E41/E$5 -> -0.041800419 | F42: =F41/F$5 -> -0.041818116 | G42: =G41/G$5 -> -0.045413191 | H42: =H41/H$5 -> -0.043424706 | I42: =I41/I$5 -> -0.043282357 | J42: =J41/J$5 -> -0.04316657 | K42: =K41/K$5 -> -0.043149475 | L42: =L41/L$5 -> -0.043004769 | ... P42: =P41/P$5 -> -0.042720167
C43: Pessoal | D43: [R$] | E43: =Histórico!E25 -> -2448000 | F43: =Histórico!F25 -> -3144592 | G43: =Histórico!G25 -> -3428891.7 | H43: =Histórico!H25 -> -3987875.6 | I43: =I44*I47 -> -4553997.5 | J43: =J44*J47 -> -5159028.6 | K43: =K44*K47 -> -5805175.8 | L43: =L44*L47 -> -6403284.9 | M43: =M44*M47 -> -7039954.3 | N43: =N44*N47 -> -7519432.3 | O43: =O44*O47 -> -8026004.6 | P43: =P44*P47 -> -8561071.6
C44: # funcionários | D44: [#] | E44: =Histórico!E26 -> 36 | F44: =Histórico!F26 -> 44 | G44: =Histórico!G26 -> 46 | H44: =Histórico!H26 -> 51 | I44: =ROUND(I8/I45,0) -> 56 | J44: =ROUND(J8/J45,0) -> 61 | K44: =ROUND(K8/K45,0) -> 66 | L44: =ROUND(L8/L45,0) -> 70 | M44: =ROUND(M8/M45,0) -> 74 | N44: =ROUND(N8/N45,0) -> 76 | O44: =ROUND(O8/O45,0) -> 78 | P44: =ROUND(P8/P45,0) -> 80
C45: Qtd vendida / func. | D45: [#] | E45: =E8/E44 -> 3376.3889 | F45: =F8/F44 -> 3337.9545 | G45: =G8/G44 -> 3355.8696 | H45: =H8/H44 -> 3419.0196 | I45: =ROUND(H45*(1+I46),0) -> 3453 | J45: =ROUND(I45*(1+J46),0) -> 3488 | K45: =ROUND(J45*(1+K46),0) -> 3523 | L45: =ROUND(K45*(1+L46),0) -> 3558 | M45: =ROUND(L45*(1+M46),0) -> 3594 | N45: =ROUND(M45*(1+N46),0) -> 3630 | O45: =ROUND(N45*(1+O46),0) -> 3666 | P45: =ROUND(O45*(1+P46),0) -> 3703
C46: Crescimento qtd vendida/ func. | D46: [%] | F46: =F45/E45-1 -> -0.011383269 | G46: =G45/F45-1 -> 0.0053670652 | H46: =H45/G45-1 -> 0.018817788 | I46: 0.01 | J46: =I46 -> 0.01 | K46: =J46 -> 0.01 | L46: =K46 -> 0.01 | M46: =L46 -> 0.01 | N46: =M46 -> 0.01 | O46: =N46 -> 0.01 | P46: =O46 -> 0.01
C47: Custo médio / funcionário | D47: [R$ / FTE] | E47: =E43/E44 -> -68000 | F47: =F43/F44 -> -71468 | G47: =G43/G44 -> -74541.124 | H47: =H43/H44 -> -78193.639 | I47: =H47*(1+I48) -> -81321.385 | J47: =I47*(1+J48) -> -84574.24 | K47: =J47*(1+K48) -> -87957.21 | L47: =K47*(1+L48) -> -91475.498 | M47: =L47*(1+M48) -> -95134.518 | N47: =M47*(1+N48) -> -98939.899 | O47: =N47*(1+O48) -> -102897.49 | P47: =O47*(1+P48) -> -107013.39
C48: Crescimento custo médio / func. | D48: [%] | F48: =F47/E47-1 -> 0.051 | G48: =G47/F47-1 -> 0.043 | H48: =H47/G47-1 -> 0.049 | I48: 0.04 | J48: =I48 -> 0.04 | K48: =J48 -> 0.04 | L48: =K48 -> 0.04 | M48: =L48 -> 0.04 | N48: =M48 -> 0.04 | O48: =N48 -> 0.04 | P48: =O48 -> 0.04
C49: Comissões | D49: [R$] | E49: =Histórico!E27 -> -4745919.8 | F49: =Histórico!F27 -> -5650030.2 | G49: =Histórico!G27 -> -7413292.6 | H49: =Histórico!H27 -> -8373750.3 | I49: =I$5*I50 -> -9707576.3 | J49: =J$5*J50 -> -11134710 | K49: =K$5*K50 -> -12552445 | L49: =L$5*L50 -> -14065782 | M49: =M$5*M50 -> -15504821 | N49: =N$5*N50 -> -16854185 | O49: =O$5*O50 -> -18160301 | P49: =P$5*P50 -> -19412494
C50: % receita bruta | D50: [%] | E50: =E49/E$5 -> -0.019 | F50: =F49/F$5 -> -0.018 | G50: =G49/G$5 -> -0.021 | H50: =H49/H$5 -> -0.02 | I50: =H50 -> -0.02 | J50: =I50 -> -0.02 | K50: =J50 -> -0.02 | L50: =K50 -> -0.02 | M50: =L50 -> -0.02 | N50: =M50 -> -0.02 | O50: =N50 -> -0.02 | P50: =O50 -> -0.02
C51: Marketing | D51: [R$] | E51: =Histórico!E28 -> -2747637.8 | F51: =Histórico!F28 -> -3766686.8 | G51: =Histórico!G28 -> -4659783.9 | H51: =Histórico!H28 -> -5233593.9 | I51: =I$5*I52 -> -6067235.2 | J51: =J$5*J52 -> -6959194 | K51: =K$5*K52 -> -7845277.9 | L51: =L$5*L52 -> -8791113.8 | M51: =M$5*M52 -> -9690513.2 | N51: =N$5*N52 -> -10533866 | O51: =O$5*O52 -> -11350188 | P51: =P$5*P52 -> -12132809
C52: % receita bruta | D52: [%] | E52: =E51/E$5 -> -0.011 | F52: =F51/F$5 -> -0.012 | G52: =G51/G$5 -> -0.0132 | H52: =H51/H$5 -> -0.0125 | I52: =H52 -> -0.0125 | J52: =I52 -> -0.0125 | K52: =J52 -> -0.0125 | L52: =K52 -> -0.0125 | M52: =L52 -> -0.0125 | N52: =M52 -> -0.0125 | O52: =N52 -> -0.0125 | P52: =O52 -> -0.0125
C53: Outros | D53: [R$] | E53: =Histórico!E29 -> -499570.5 | F53: =Histórico!F29 -> -565003.02 | G53: =Histórico!G29 -> -529520.9 | H53: =Histórico!H29 -> -586162.52 | I53: =I$5*I54 -> -679530.34 | J53: =J$5*J54 -> -779429.73 | K53: =K$5*K54 -> -878671.12 | L53: =L$5*L54 -> -984604.75 | M53: =M$5*M54 -> -1085337.5 | N53: =N$5*N54 -> -1179793 | O53: =O$5*O54 -> -1271221.1 | P53: =P$5*P54 -> -1358874.6
C54: % receita bruta | D54: [%] | E54: =E53/E$5 -> -0.002 | F54: =F53/F$5 -> -0.0018 | G54: =G53/G$5 -> -0.0015 | H54: =H53/H$5 -> -0.0014 | I54: =H54 -> -0.0014 | J54: =I54 -> -0.0014 | K54: =J54 -> -0.0014 | L54: =K54 -> -0.0014 | M54: =L54 -> -0.0014 | N54: =M54 -> -0.0014 | O54: =N54 -> -0.0014 | P54: =O54 -> -0.0014
C56: Despesas gerais e administrativas | D56: [R$] | E56: =SUM(E58,E68,E70,E63) -> -8836389.4 | F56: =SUM(F58,F68,F70,F63) -> -9411322.1 | G56: =SUM(G58,G68,G70,G63) -> -10070627 | H56: =SUM(H58,H68,H70,H63) -> -10891061 | I56: =SUM(I58,I68,I70,I63) -> -11326704 | J56: =SUM(J58,J68,J70,J63) -> -11779772 | K56: =SUM(K58,K68,K70,K63) -> -12449057 | L56: =SUM(L58,L68,L70,L63) -> -12947019 | ... P56: =SUM(P58,P68,P70,P63) -> -15628206
C57: % receita bruta | D57: [%] | E57: =E56/E$5 -> -0.035375945 | F57: =F56/F$5 -> -0.029982813 | G57: =G56/G$5 -> -0.028527561 | H57: =H56/H$5 -> -0.026012386 | I57: =I56/I$5 -> -0.023335801 | J57: =J56/J$5 -> -0.02115865 | K57: =K56/K$5 -> -0.019835271 | L57: =L56/L$5 -> -0.018409242 | ... P57: =P56/P$5 -> -0.016101183
C58: Pessoal | D58: [R$] | E58: =Histórico!E32 -> -4743000 | F58: =Histórico!F32 -> -4824090 | G58: =Histórico!G32 -> -5211705.6 | H58: =Histórico!H32 -> -5635366.9 | I58: =I60*I61 -> -5860781.5 | J58: =J60*J61 -> -6095212.8 | K58: =K60*K61 -> -6537115.7 | L58: =L60*L61 -> -6798600.4 | M58: =M60*M61 -> -7070544.4 | N58: =N60*N61 -> -7576195.4 | O58: =O60*O61 -> -7879243.2 | P58: =P60*P61 -> -8435425.1
C59: % receita bruta | D59: [%] | E59: =E58/E$5 -> -0.018988311 | F59: =F58/F$5 -> -0.0153687 | G59: =G58/G$5 -> -0.014763456 | H59: =H58/H$5 -> -0.013459601 | I59: =I58/I$5 -> -0.012074655 | J59: =J58/J$5 -> -0.01094813 | K59: =K58/K$5 -> -0.010415685 | L59: =L58/L$5 -> -0.0096668643 | ... P59: =P58/P$5 -> -0.0086907175
C60: # funcionários | D60: [#] | E60: =Histórico!E33 -> 31 | F60: =Histórico!F33 -> 30 | G60: =Histórico!G33 -> 31 | H60: =Histórico!H33 -> 32 | I60: 32 | J60: 32 | K60: 33 | L60: 33 | M60: 33 | N60: 34 | O60: 34 | P60: 35
C61: Custo médio / funcionário | D61: [R$ / FTE] | E61: =E58/E60 -> -153000 | F61: =F58/F60 -> -160803 | G61: =G58/G60 -> -168119.54 | H61: =H58/H60 -> -176105.21 | I61: =H61*(1+I62) -> -183149.42 | J61: =I61*(1+J62) -> -190475.4 | K61: =J61*(1+K62) -> -198094.42 | L61: =K61*(1+L62) -> -206018.19 | M61: =L61*(1+M62) -> -214258.92 | N61: =M61*(1+N62) -> -222829.28 | O61: =N61*(1+O62) -> -231742.45 | P61: =O61*(1+P62) -> -241012.15
C62: Crescimento custo médio / func. | D62: [%] | F62: =F61/E61-1 -> 0.051 | G62: =G61/F61-1 -> 0.0455 | H62: =H61/G61-1 -> 0.0475 | I62: 0.04 | J62: =I62 -> 0.04 | K62: =J62 -> 0.04 | L62: =K62 -> 0.04 | M62: =L62 -> 0.04 | N62: =M62 -> 0.04 | O62: =N62 -> 0.04 | P62: =O62 -> 0.04
C63: Diretoria | D63: [R$] | E63: =Histórico!E34 -> -1680000 | F63: =Histórico!F34 -> -1764000 | G63: =Histórico!G34 -> -1834560 | H63: =Histórico!H34 -> -1917115.2 | I63: =I65*I66 -> -1993799.8 | J63: =J65*J66 -> -2073551.8 | K63: =K65*K66 -> -2156493.9 | L63: =L65*L66 -> -2242753.6 | M63: =M65*M66 -> -2332463.8 | N63: =N65*N66 -> -2425762.3 | O63: =O65*O66 -> -2522792.8 | P63: =P65*P66 -> -2623704.5
C64: % receita bruta | D64: [%] | E64: =E63/E$5 -> -0.0067257774 | F64: =F63/F$5 -> -0.005619793 | G64: =G63/G$5 -> -0.0051968487 | H64: =H63/H$5 -> -0.0045788688 | I64: =I63/I$5 -> -0.0041077191 | J64: =J63/J$5 -> -0.0037244827 | K64: =K63/K$5 -> -0.0034359743 | L64: =L63/L$5 -> -0.0031889498 | ... P64: =P63/P$5 -> -0.0027031092
C65: # funcionários | D65: [#] | E65: =Histórico!E35 -> 4 | F65: =Histórico!F35 -> 4 | G65: =Histórico!G35 -> 4 | H65: =Histórico!H35 -> 4 | I65: =H65 -> 4 | J65: =I65 -> 4 | K65: =J65 -> 4 | L65: =K65 -> 4 | M65: =L65 -> 4 | N65: =M65 -> 4 | O65: =N65 -> 4 | P65: =O65 -> 4
C66: Custo médio / funcionário | D66: [R$ / FTE] | E66: =E63/E65 -> -420000 | F66: =F63/F65 -> -441000 | G66: =G63/G65 -> -458640 | H66: =H63/H65 -> -479278.8 | I66: =H66*(1+I67) -> -498449.95 | J66: =I66*(1+J67) -> -518387.95 | K66: =J66*(1+K67) -> -539123.47 | L66: =K66*(1+L67) -> -560688.41 | M66: =L66*(1+M67) -> -583115.94 | N66: =M66*(1+N67) -> -606440.58 | O66: =N66*(1+O67) -> -630698.2 | P66: =O66*(1+P67) -> -655926.13
C67: Crescimento custo médio / func. | D67: [%] | F67: =F66/E66-1 -> 0.05 | G67: =G66/F66-1 -> 0.04 | H67: =H66/G66-1 -> 0.045 | I67: 0.04 | J67: =I67 -> 0.04 | K67: =J67 -> 0.04 | L67: =K67 -> 0.04 | M67: =L67 -> 0.04 | N67: =M67 -> 0.04 | O67: =N67 -> 0.04 | P67: =O67 -> 0.04
C68: Aluguéis e utilidades | D68: [R$] | E68: =Histórico!E36 -> -540000 | F68: =Histórico!F36 -> -563220 | G68: =Histórico!G36 -> -588564.9 | H68: =Histórico!H36 -> -617110.3 | I68: =H68*(1+I69) -> -641794.71 | J68: =I68*(1+J69) -> -667466.5 | K68: =J68*(1+K69) -> -694165.16 | L68: =K68*(1+L69) -> -721931.76 | M68: =L68*(1+M69) -> -750809.03 | N68: =M68*(1+N69) -> -780841.4 | O68: =N68*(1+O69) -> -812075.05 | P68: =O68*(1+P69) -> -844558.05
C69: % crescimento | D69: [%] | F69: =F68/E68-1 -> 0.043 | G69: =G68/F68-1 -> 0.045 | H69: =H68/G68-1 -> 0.0485 | I69: 0.04 | J69: =I69 -> 0.04 | K69: =J69 -> 0.04 | L69: =K69 -> 0.04 | M69: =L69 -> 0.04 | N69: =M69 -> 0.04 | O69: =N69 -> 0.04 | P69: =O69 -> 0.04
C70: Gerais e administrativas | D70: [R$] | E70: =Histórico!E37 -> -1873389.4 | F70: =Histórico!F37 -> -2260012.1 | G70: =Histórico!G37 -> -2435796.1 | H70: =Histórico!H37 -> -2721468.8 | I70: =H70*(1+I71) -> -2830327.6 | J70: =I70*(1+J71) -> -2943540.7 | K70: =J70*(1+K71) -> -3061282.3 | L70: =K70*(1+L71) -> -3183733.6 | M70: =L70*(1+M71) -> -3311083 | N70: =M70*(1+N71) -> -3443526.3 | O70: =N70*(1+O71) -> -3581267.3 | P70: =O70*(1+P71) -> -3724518
C71: % crescimento | D71: [%] | F71: =F70/E70-1 -> 0.20637604 | G71: =G70/F70-1 -> 0.077780151 | H71: =H70/G70-1 -> 0.11728104 | I71: 0.04 | J71: =I71 -> 0.04 | K71: =J71 -> 0.04 | L71: =K71 -> 0.04 | M71: =L71 -> 0.04 | N71: =M71 -> 0.04 | O71: =N71 -> 0.04 | P71: =O71 -> 0.04
C73: EBITDA | D73: [R$] | E73: =E35+E38 -> 21145887 | F73: =F35+F38 -> 33438622 | G73: =G35+G38 -> 34674282 | H73: =H35+H38 -> 42896067 | I73: =I35+I38 -> 51179598 | J73: =J35+J38 -> 60057178 | K73: =K35+K38 -> 68673540 | L73: =L35+L38 -> 78133890 | ... P73: =P35+P38 -> 1.1080389e+08
C74: Margem EBITDA | D74: [%] | E74: =E73/E$20 -> 0.11148762 | F74: =F73/F$20 -> 0.14065164 | G74: =G73/G$20 -> 0.1286322 | H74: =H73/H$20 -> 0.1348666 | I74: =I73/I$20 -> 0.13880113 | J74: =J73/J$20 -> 0.1420015 | K74: =K73/K$20 -> 0.144035 | L74: =L73/L$20 -> 0.14624549 | ... P74: =P73/P$20 -> 0.15027288
C76: Depreciação e amortização | D76: [R$] | E76: =Histórico!E41 -> -4242317.1 | F76: =Histórico!F41 -> -4534028.1 | G76: =Histórico!G41 -> -4946712.8 | H76: =Histórico!H41 -> -5525365.7 | I76: =-I157 -> -6226017.1 | J76: =-J157 -> -7033655.7 | K76: =-K157 -> -7873197 | L76: =-L157 -> -8777167 | M76: =-M157 -> -6350506.6 | N76: =-N157 -> -5498936.6 | O76: =-O157 -> -6782799.9 | P76: =-P157 -> -8155840.7
C78: EBIT | D78: [R$] | E78: =E73+E76 -> 16903570 | F78: =F73+F76 -> 28904594 | G78: =G73+G76 -> 29727569 | H78: =H73+H76 -> 37370702 | I78: =I73+I76 -> 44953581 | J78: =J73+J76 -> 53023522 | K78: =K73+K76 -> 60800343 | L78: =L73+L76 -> 69356723 | ... P78: =P73+P76 -> 1.0264805e+08
C79: Margem EBIT | D79: [%] | E79: =E78/E$20 -> 0.08912082 | F79: =F78/F$20 -> 0.12158033 | G79: =G78/G$20 -> 0.11028124 | H79: =H78/H$20 -> 0.11749467 | I79: =I78/I$20 -> 0.12191592 | J79: =J78/J$20 -> 0.12537085 | K79: =K78/K$20 -> 0.12752186 | L79: =L78/L$20 -> 0.12981701 | ... P79: =P78/P$20 -> 0.13921188
C81: Resultado financeiro | D81: [R$] | E81: =E82+E83 -> -4128014.9 | F81: =F82+F83 -> -8937381.8 | G81: =G82+G83 -> -6148781.1 | H81: =H82+H83 -> -4540838.1 | I81: =I82+I83 -> 0 | J81: =J82+J83 -> 0 | K81: =K82+K83 -> 0 | L81: =L82+L83 -> 0 | ... P81: =P82+P83 -> 0
C82: Receitas financeiras | D82: [R$] | E82: =Histórico!E46 -> 101162.48 | F82: =Histórico!F46 -> 91046.232 | G82: =Histórico!G46 -> 924772.39 | H82: =Histórico!H46 -> 606689.94
C83: Despesas financeiras | D83: [R$] | E83: =Histórico!E47 -> -4229177.4 | F83: =Histórico!F47 -> -9028428 | G83: =Histórico!G47 -> -7073553.5 | H83: =Histórico!H47 -> -5147528.1
C85: Resultado não-operacional | D85: [R$] | E85: =E86+E87 -> 0 | F85: =F86+F87 -> -1242590 | G85: =G86+G87 -> -227000 | H85: =H86+H87 -> -150000 | I85: =I86+I87 -> 0 | J85: =J86+J87 -> 0 | K85: =K86+K87 -> 0 | L85: =L86+L87 -> 0 | ... P85: =P86+P87 -> 0
C86: Outras receitas | D86: [R$] | E86: =Histórico!E50 -> 0 | F86: =Histórico!F50 -> 0 | G86: =Histórico!G50 -> 200000 | H86: =Histórico!H50 -> 45000
C87: Outras despesas | D87: [R$] | E87: =Histórico!E51 -> 0 | F87: =Histórico!F51 -> -1242590 | G87: =Histórico!G51 -> -427000 | H87: =Histórico!H51 -> -195000
C89: LAIR | D89: [R$] | E89: =E78+E81+E85 -> 12775555 | F89: =F78+F81+F85 -> 18724623 | G89: =G78+G81+G85 -> 23351788 | H89: =H78+H81+H85 -> 32679864 | I89: =I78+I81+I85 -> 44953581 | J89: =J78+J81+J85 -> 53023522 | K89: =K78+K81+K85 -> 60800343 | L89: =L78+L81+L85 -> 69356723 | ... P89: =P78+P81+P85 -> 1.0264805e+08
C90: IR/CSLL | D90: [R$] | E90: =Histórico!E54 -> -4265757.7 | F90: =Histórico!F54 -> -6263386.2 | G90: =Histórico!G54 -> -7846200.7 | H90: =Histórico!H54 -> -11045794 | I90: =IF(I89<0,0,IF(I89>=0,I89*I91)) -> -15284218 | J90: =IF(J89<0,0,IF(J89>=0,J89*J91)) -> -18027998 | K90: =IF(K89<0,0,IF(K89>=0,K89*K91)) -> -20672117 | L90: =IF(L89<0,0,IF(L89>=0,L89*L91)) -> -23581286 | M90: =IF(M89<0,0,IF(M89>=0,M89*M91)) -> -27444900 | N90: =IF(N89<0,0,IF(N89>=0,N89*N91)) -> -30551231 | O90: =IF(O89<0,0,IF(O89>=0,O89*O91)) -> -32877521 | P90: =IF(P89<0,0,IF(P89>=0,P89*P91)) -> -34900337
C91: % LAIR | D91: [%] | E91: =E90/E89 -> -0.3339 | F91: =F90/F89 -> -0.3345 | G91: =G90/G89 -> -0.336 | H91: =H90/H89 -> -0.338 | I91: -0.34 | J91: =I91 -> -0.34 | K91: =J91 -> -0.34 | L91: =K91 -> -0.34 | M91: =L91 -> -0.34 | N91: =M91 -> -0.34 | O91: =N91 -> -0.34 | P91: =O91 -> -0.34
C93: Lucro Líquido | D93: [R$] | E93: =E89+E90 -> 8509797 | F93: =F89+F90 -> 12461236 | G93: =G89+G90 -> 15505587 | H93: =H89+H90 -> 21634070 | I93: =I89+I90 -> 29669364 | J93: =J89+J90 -> 34995525 | K93: =K89+K90 -> 40128227 | L93: =L89+L90 -> 45775437 | ... P93: =P89+P90 -> 67747714
C94: Margem líquida | D94: [%] | E94: =E93/E$20 -> 0.044866268 | F94: =F93/F$20 -> 0.052415239 | G94: =G93/G$20 -> 0.057521533 | H94: =H93/H$20 -> 0.068018201 | I94: =I93/I$20 -> 0.080464505 | J94: =J93/J$20 -> 0.082744762 | K94: =K93/K$20 -> 0.084164428 | L94: =L93/L$20 -> 0.085679227 | ... P94: =P93/P$20 -> 0.091879841
C95: Check | D95: =SUM(E95:H95) -> 0 | E95: =Histórico!E56-E93 -> 0 | F95: =Histórico!F56-F93 -> 0 | G95: =Histórico!G56-G93 -> 0 | H95: =Histórico!H56-H93 -> 0
E98: Histórico | I98: Projeções
D99: Unit | E99: =E3 -> 2015 | F99: =F3 -> 2016 | G99: =G3 -> 2017 | H99: =H3 -> 2018 | I99: =I3 -> 2019E | J99: =J3 -> 2020E | K99: =K3 -> 2021E | L99: =L3 -> 2022E | ... P99: =P3 -> 2026E
B100: BALANÇO PATRIMONIAL
C101: ATIVO | D101: [R$] | E101: =SUM(E102,E108) -> 1.0009875e+08 | F101: =SUM(F102,F108) -> 1.4312784e+08 | G101: =SUM(G102,G108) -> 1.4408256e+08 | H101: =SUM(H102,H108) -> 1.5614796e+08 | I101: =SUM(I102,I108) -> 1.9296676e+08 | J101: =SUM(J102,J108) -> 2.3542689e+08 | K101: =SUM(K102,K108) -> 2.8297852e+08 | L101: =SUM(L102,L108) -> 3.3666528e+08 | ... P101: =SUM(P102,P108) -> 6.0892473e+08
C102: ATVO CIRCULANTE | D102: [R$] | E102: =SUM(E103:E106) -> 74008987 | F102: =SUM(F103:F106) -> 1.1859014e+08 | G102: =SUM(G103:G106) -> 1.1956703e+08 | H102: =SUM(H103:H106) -> 1.3096122e+08 | I102: =SUM(I103:I106) -> 1.6682243e+08 | J102: =SUM(J103:J106) -> 2.0807653e+08 | K102: =SUM(K103:K106) -> 2.5421255e+08 | L102: =SUM(L103:L106) -> 3.062678e+08 | ... P102: =SUM(P103:P106) -> 5.535658e+08
C103: Caixa e equivalentes | D103: [R$] | E103: =Histórico!E63 -> 2529062 | F103: =Histórico!F63 -> 25688122 | G103: =Histórico!G63 -> 16852498 | H103: =Histórico!H63 -> 9115958.5 | I103: =H103+I209 -> 25654194 | J103: =I103+J209 -> 46233577 | K103: =J103+K209 -> 71831059 | L103: =K103+L209 -> 1.0196278e+08 | M103: =L103+M209 -> 1.3690743e+08 | N103: =M103+N209 -> 1.7680848e+08 | O103: =N103+O209 -> 2.2186123e+08 | P103: =O103+P209 -> 2.7180363e+08
C104: Contas a receber | D104: [R$] | E104: =Histórico!E64 -> 47875506 | F104: =Histórico!F64 -> 61295852 | G104: =Histórico!G64 -> 67661004 | H104: =Histórico!H64 -> 82574482 | I104: =I5*I132/360 -> 95727488 | J104: =J5*J132/360 -> 1.0980062e+08 | K104: =K5*K132/360 -> 1.2378105e+08 | L104: =L5*L132/360 -> 1.3870424e+08 | M104: =M5*M132/360 -> 1.5289476e+08 | N104: =N5*N132/360 -> 1.6620099e+08 | O104: =O5*O132/360 -> 1.7908075e+08 | P104: =P5*P132/360 -> 1.9142876e+08
C105: Estoque | D105: [R$] | E105: =Histórico!E65 -> 23075439 | F105: =Histórico!F65 -> 30948215 | G105: =Histórico!G65 -> 34575165 | H105: =Histórico!H65 -> 38734992 | I105: =-I26*I133/360 -> 44904956 | J105: =-J26*J133/360 -> 51506541 | K105: =-K26*K133/360 -> 58064645 | L105: =-L26*L133/360 -> 65064987 | M105: =-M26*M133/360 -> 71721641 | N105: =-N26*N133/360 -> 77963481 | O105: =-O26*O133/360 -> 84005264 | P105: =-P26*P133/360 -> 89797614
C106: Outros | D106: [R$] | E106: =Histórico!E66 -> 528980 | F106: =Histórico!F66 -> 657956 | G106: =Histórico!G66 -> 478362 | H106: =Histórico!H66 -> 535791 | I106: =H106 -> 535791 | J106: =I106 -> 535791 | K106: =J106 -> 535791 | L106: =K106 -> 535791 | M106: =L106 -> 535791 | N106: =M106 -> 535791 | O106: =N106 -> 535791 | P106: =O106 -> 535791
C108: ATIVO NÃO CIRCULANTE | D108: [R$] | E108: =SUM(E109:E112) -> 26089767 | F108: =SUM(F109:F112) -> 24537700 | G108: =SUM(G109:G112) -> 24515531 | H108: =SUM(H109:H112) -> 25186741 | I108: =SUM(I109:I112) -> 26144330 | J108: =SUM(J109:J112) -> 27350360 | K108: =SUM(K109:K112) -> 28765972 | L108: =SUM(L109:L112) -> 30397484 | ... P108: =SUM(P109:P112) -> 55358933
C109: Imobilizado | D109: [R$] | E109: =Histórico!E69 -> 42977454 | F109: =Histórico!F69 -> 45771081 | G109: =Histórico!G69 -> 50536769 | H109: =Histórico!H69 -> 56440263 | I109: =H109+I151 -> 63284104 | J109: =I109+J151 -> 71134075 | K109: =J109+K151 -> 79983548 | L109: =K109+L151 -> 89899924 | M109: =L109+M151 -> 1.0083082e+08 | N109: =M109+N151 -> 1.1271302e+08 | O109: =N109+O151 -> 1.2551604e+08 | P109: =O109+P151 -> 1.3920184e+08
C110: (-) Depreciação acumulada | D110: [R$] | E110: =Histórico!E70 -> -17190982 | F110: =Histórico!F70 -> -21628409 | G110: =Histórico!G70 -> -26443801 | H110: =Histórico!H70 -> -31792653 | I110: =H110-I158 -> -37778871 | J110: =I110-J158 -> -44499780 | K110: =J110-K158 -> -52055661 | L110: =K110-L158 -> -60549835 | M110: =L110-M158 -> -66513851 | N110: =M110-N158 -> -71547017 | O110: =N110-O158 -> -77814444 | P110: =O110-P158 -> -85406311
C111: Intangível | D111: [R$] | E111: =Histórico!E71 -> 388839.41 | F111: =Histórico!F71 -> 577173.75 | G111: =Histórico!G71 -> 736030.02 | H111: =Histórico!H71 -> 1029111.3 | I111: =H111+I154 -> 1368876.5 | J111: =I111+J154 -> 1758591.3 | K111: =J111+K154 -> 2197926.9 | L111: =K111+L154 -> 2690229.2 | M111: =L111+M154 -> 3232898 | N111: =M111+N154 -> 3822794.5 | O111: =N111+O154 -> 4458405 | P111: =O111+P154 -> 5137842.3
C112: (-) Amortização acumulada | D112: [R$] | E112: =Histórico!E72 -> -85544.671 | F112: =Histórico!F72 -> -182145.99 | G112: =Histórico!G72 -> -313466.36 | H112: =Histórico!H72 -> -489980.49 | I112: =H112-I172 -> -729779.27 | J112: =I112-J172 -> -1042526 | K112: =J112-K172 -> -1359841.9 | L112: =K112-L172 -> -1642835.2 | M112: =L112-M172 -> -2029325.7 | N112: =M112-N172 -> -2495096.2 | O112: =N112-O172 -> -3010469.3 | P112: =O112-P172 -> -3574442.3
C114: PASSIVO | D114: [R$] | E114: =SUM(E115,E122,E125) -> 1.0009875e+08 | F114: =SUM(F115,F122,F125) -> 1.4312784e+08 | G114: =SUM(G115,G122,G125) -> 1.4408256e+08 | H114: =SUM(H115,H122,H125) -> 1.5614796e+08 | I114: =SUM(I115,I122,I125) -> 1.9296676e+08 | J114: =SUM(J115,J122,J125) -> 2.3542689e+08 | K114: =SUM(K115,K122,K125) -> 2.8297852e+08 | L114: =SUM(L115,L122,L125) -> 3.3666528e+08 | ... P114: =SUM(P115,P122,P125) -> 6.0892473e+08
C115: PASSIVO CIRCULANTE | D115: [R$] | E115: =SUM(E116:E120) -> 46861067 | F115: =SUM(F116:F120) -> 81535612 | G115: =SUM(G116:G120) -> 72751268 | H115: =SUM(H116:H120) -> 74992286 | I115: =SUM(I116:I120) -> 82141718 | J115: =SUM(J116:J120) -> 89606319 | K115: =SUM(K116:K120) -> 97029726 | L115: =SUM(L116:L120) -> 1.0494105e+08 | ... P115: =SUM(P116:P120) -> 1.3305099e+08
C116: Contas a pagar | D116: [R$] | E116: =Histórico!E76 -> 19892620 | F116: =Histórico!F76 -> 23211161 | G116: =Histórico!G76 -> 25652542 | H116: =Histórico!H76 -> 30856688 | I116: =-I26*I134/360 -> 35771744 | J116: =-J26*J134/360 -> 41030634 | K116: =-K26*K134/360 -> 46254887 | L116: =-L26*L134/360 -> 51831430 | M116: =-M26*M134/360 -> 57134189 | N116: =-N26*N134/360 -> 62106502 | O116: =-O26*O134/360 -> 66919448 | P116: =-P26*P134/360 -> 71533692
C117: Obrigações trabalhistas | D117: [R$] | E117: =Histórico!E77 -> 1116825 | F117: =Histórico!F77 -> 1402748.7 | G117: =Histórico!G77 -> 1798725.4 | H117: =Histórico!H77 -> 1773807.8 | I117: =-I138*I135/360 -> 1968641.9 | J117: =-J138*J135/360 -> 2176224.7 | K117: =-K138*K135/360 -> 2398796.4 | L117: =-L138*L135/360 -> 2614794.5 | M117: =-M138*M135/360 -> 2823987.3 | N117: =-N138*N135/360 -> 3026754 | O117: =-O138*O135/360 -> 3213152.1 | P117: =-P138*P135/360 -> 3429703.5
C118: Obrigações fiscais | D118: [R$] | E118: =Histórico!E78 -> 6619970.1 | F118: =Histórico!F78 -> 8982642.7 | G118: =Histórico!G78 -> 9661232.9 | H118: =Histórico!H78 -> 11204697 | I118: =-I144*I136/360 -> 13244238 | J118: =-J144*J136/360 -> 15242367 | K118: =-K144*K136/360 -> 17218949 | L118: =-L144*L136/360 -> 19337735 | M118: =-M144*M136/360 -> 21465273 | N118: =-N144*N136/360 -> 23407145 | O118: =-O144*O136/360 -> 25216840 | P118: =-P144*P136/360 -> 26930503
C119: Empréstimos e financiamentos | D119: [R$] | E119: =Histórico!E79 -> 19031298 | F119: =Histórico!F79 -> 47650037 | G119: =Histórico!G79 -> 35367767 | H119: =Histórico!H79 -> 30885169 | I119: =H119 -> 30885169 | J119: =I119 -> 30885169 | K119: =J119 -> 30885169 | L119: =K119 -> 30885169 | M119: =L119 -> 30885169 | N119: =M119 -> 30885169 | O119: =N119 -> 30885169 | P119: =O119 -> 30885169
C120: Outros | D120: [R$] | E120: =Histórico!E80 -> 200354 | F120: =Histórico!F80 -> 289023 | G120: =Histórico!G80 -> 271000 | H120: =Histórico!H80 -> 271925 | I120: =H120 -> 271925 | J120: =I120 -> 271925 | K120: =J120 -> 271925 | L120: =K120 -> 271925 | M120: =L120 -> 271925 | N120: =M120 -> 271925 | O120: =N120 -> 271925 | P120: =O120 -> 271925
...
